{
  "title": "Blacklight Inspection",
  "page_title": "Mercado Libre Argentina - Envíos Gratis en el día",
  "uri_ins": "https://mercadolibre.com.ar",
  "uri_dest": "https://www.mercadolibre.com.ar/?skipInApp=true",
  "uri_redirects": [],
  "secure_connection": {},
  "host": "mercadolibre.com.ar",
  "config": {
    "emulateDevice": {
      "name": "iPhone 13 Mini",
      "userAgent": "Mozilla/5.0 (iPhone; CPU iPhone OS 15_0 like Mac OS X) AppleWebKit/605.1.15 (KHTML, like Gecko) Version/15.4 Mobile/15E148 Safari/604.1",
      "viewport": {
        "width": 375,
        "height": 812,
        "deviceScaleFactor": 3,
        "isMobile": true,
        "hasTouch": true,
        "isLandscape": false
      }
    },
    "cleareCache": true,
    "captureHar": true,
    "captureLinks": false,
    "enableAdBlock": false,
    "saveBrowserProfile": false,
    "numPages": 0,
    "defaultTimeout": 35000,
    "defaultWaitUntil": "networkidle2",
    "headless": true,
    "headers": {},
    "extraChromiumArgs": [
      "--disable-features=TrackingProtection3pcd"
    ],
    "extraPuppeteerOptions": {}
  },
  "browser": {
    "name": "Chromium",
    "version": "Chrome/127.0.6533.88",
    "user_agent": "Mozilla/5.0 (X11; Linux x86_64) AppleWebKit/537.36 (KHTML, like Gecko) HeadlessChrome/127.0.0.0 Safari/537.36",
    "platform": {
      "name": "Linux",
      "version": "6.18.5-200.fc43.x86_64"
    }
  },
  "script": {
    "host": "fedora",
    "version": {
      "npm": "3.9.0",
      "commit": "dev"
    },
    "node_version": "v22.20.0"
  },
  "start_time": "2026-06-11T10:26:39.522Z",
  "end_time": "2026-06-11T10:26:45.831Z",
  "browsing_history": [
    "https://www.mercadolibre.com.ar/?skipInApp=true"
  ],
  "hosts": {
    "requests": {
      "first_party": [
        "mercadolibre.com.ar",
        "www.mercadolibre.com.ar",
        "matt.mercadolibre.com.ar"
      ],
      "third_party": [
        "http2.mlstatic.com",
        "print1.mercadoclics.com",
        "api.mercadolibre.com",
        "home",
        "o11y-proxy-otel-frontend.meli.com"
      ]
    }
  },
  "reports": {
    "behaviour_event_listeners": {
      "MOUSE": {
        "https://http2.mlstatic.com/frontend-assets/ml-web-navigation/widgets/7.31.1/searchbox.js": [
          "mousedown"
        ],
        "https://http2.mlstatic.com/storage/melidata-js-sdk/js/3/0.7.7/melidata.min.js": [
          "click"
        ],
        "https://http2.mlstatic.com/frontend-assets/web-monitoring/1.5.7/web_vitals.min.js": [
          "click"
        ]
      },
      "KEYBOARD": {
        "https://http2.mlstatic.com/storage/melidata-js-sdk/js/3/0.7.7/melidata.min.js": [
          "keydown"
        ],
        "https://http2.mlstatic.com/frontend-assets/cookies-consent-banner-builder/1.0.0-beta.3/cookie-consent-banner-opt-out/script.js": [
          "keydown"
        ],
        "https://http2.mlstatic.com/frontend-assets/web-monitoring/1.5.7/web_vitals.min.js": [
          "keydown"
        ]
      }
    },
    "canvas_fingerprinters": {
      "data_url": {},
      "fingerprinters": [],
      "styles": {},
      "texts": {}
    },
    "canvas_font_fingerprinters": {
      "canvas_font": {},
      "text_measure": {}
    },
    "cookies": [
      {
        "name": "_d2id",
        "value": "aa547b97-b7c6-4932-b7af-d6e20392aafd-n",
        "domain": "mercadolibre.com.ar",
        "path": "/",
        "expires": "2027-06-11T10:26:40.725Z",
        "size": 43,
        "httpOnly": false,
        "secure": true,
        "session": false,
        "sameSite": "None",
        "priority": "Medium",
        "sameParty": false,
        "sourceScheme": "Secure",
        "sourcePort": 443,
        "type": "unknown",
        "third_party": false
      },
      {
        "name": "_csrf",
        "value": "be4o2E3BrsDxSzg8TqgKhN-A",
        "domain": "www.mercadolibre.com.ar",
        "path": "/",
        "expires": -1,
        "size": 29,
        "httpOnly": true,
        "secure": true,
        "session": true,
        "sameSite": "None",
        "priority": "Medium",
        "sameParty": false,
        "sourceScheme": "Secure",
        "sourcePort": 443,
        "type": "unknown",
        "third_party": false
      },
      {
        "name": "_mldataSessionId",
        "value": "538aa6f3-583b-4270-83b0-7167e4913f7f",
        "domain": "mercadolibre.com.ar",
        "path": "/",
        "expires": "2026-06-11T10:56:43.000Z",
        "size": 52,
        "httpOnly": false,
        "secure": true,
        "session": false,
        "sameSite": "None",
        "priority": "Medium",
        "sameParty": false,
        "sourceScheme": "Secure",
        "sourcePort": 443,
        "type": "js",
        "third_party": false
      },
      {
        "name": "in_app",
        "value": "true",
        "domain": "mercadolibre.com.ar",
        "path": "/",
        "expires": "2026-06-12T10:26:40.725Z",
        "size": 10,
        "httpOnly": false,
        "secure": true,
        "session": false,
        "sameSite": "None",
        "priority": "Medium",
        "sameParty": false,
        "sourceScheme": "Secure",
        "sourcePort": 443,
        "type": "unknown",
        "third_party": false
      },
      {
        "name": "c_2hU8zU",
        "value": "1",
        "domain": "www.mercadolibre.com.ar",
        "path": "/",
        "expires": "2026-07-11T10:26:40.726Z",
        "size": 9,
        "httpOnly": true,
        "secure": true,
        "session": false,
        "sameSite": "None",
        "priority": "Medium",
        "sameParty": false,
        "sourceScheme": "Secure",
        "sourcePort": 443,
        "type": "unknown",
        "third_party": false
      },
      {
        "name": "c_xe42xnaFXxBAzUzt0QGr5g",
        "value": "polycard-web-lib%2F2.52.0",
        "domain": "www.mercadolibre.com.ar",
        "path": "/",
        "expires": "2026-07-11T10:26:42.533Z",
        "size": 49,
        "httpOnly": true,
        "secure": true,
        "session": false,
        "priority": "Medium",
        "sameParty": false,
        "sourceScheme": "Secure",
        "sourcePort": 443,
        "type": "unknown",
        "third_party": false
      },
      {
        "name": "_d2id",
        "value": "6a2084dd-b62e-4e4a-9c46-c746c8859187-n",
        "domain": "mercadoclics.com",
        "path": "/",
        "expires": "2027-06-11T10:26:41.332Z",
        "size": 43,
        "httpOnly": false,
        "secure": true,
        "session": false,
        "sameSite": "None",
        "priority": "Medium",
        "sameParty": false,
        "sourceScheme": "Secure",
        "sourcePort": 443,
        "type": "unknown",
        "third_party": true
      }
    ],
    "fb_pixel_events": [],
    "google_analytics_events": [],
    "key_logging": {},
    "session_recorders": {},
    "third_party_trackers": [
      {
        "data": {
          "filter": "||mercadoclics.com^$third-party",
          "listName": "easyprivacy.txt",
          "query": {
            "d": "wFUQPrJjQfwHCp9brC6qr6wwcy6FuEm1pP9cn1rSmEWielVuHSJrTToutpQkxwuXrlGmV8qg3myf3XIOTJYewag_4nI6mnx2uMaNiVXWliOxi3EMe0oLeN-Bj3IH-PkGM48igINhcGQgZWhvFAQxEscc-33dUFnn4RsgjKBtFkpIpBwi8NfigvbfnZnG_3FcZG0gwoUK1ZqLpF8rkRxevGLlv1g9Ob7Laap0NygVsdbupd0SZaKBHO3sBP1736lg4-_btrAY_2E_W94aP5OO2AITZuWkUxlize4dxieufcRUOfUtDFS5Q3vI3sTzOoTeYOWsbHJl6_SlSWetpE_BDiosu0jSVJKHrcuJbNjv1JxjmlqQZuh3HMibUVzzdzkzDeMKswXKf5eZoW0zPvf8N9z3V_ec6vSZhv2bCin_GN36BUoGVGg5fY5_cEql03atumRBXZ2IBbbjTCTGZoAHYzV2i-4wXI-cyvYPOuudhbcz4VX-RF2TlvcnN1j3zK5fs2-bdD-fEThFGLEVmwEHOQSjAQ5luq6uTUjukry66WZVtVVC6Vc6YbF_nzA17yJOzZyhh1_k7CMIhthOF_m13uy1y3W5BccLOGsQwmr1HKN0Q2lC68nk8ZGMsqXIZONlOK_vjrnyItX6ZKaKuuueDvJnij1xF3eQaxMbOirvVqeUFEZ2YdA8Vf6i-kSQ-2nsAI9VT1duUNbkHH0FhL78DQCIciIrSc-gUyfUFNlVWM22Nn50duQgL41Zp2NPeelOYZF4ysAp5Opv3gOXWFX4n0SO8g1mMfiIw4DSFxEeHTtxyHtpdEcOHolB3n9Lz22DOcwx9xTuUAVHvjFHzc03FZ8IDJ7YVESY7p7AIuaEpWzdYs0qryEcn-0deM5mbwGktoj-86a02QIlRZKlUQc-mNYOlWqd9EPGa766Z6T72a_Bjh2H0VNLAzmvqss6EaHQpr88p25dM3nmeh-dIciwCc3dfdO4kzzjaX833RZsv3uFCSxoCK7R-UwR_W02AaytORJlsMlD7KunWSIRUh2syAW4f-xOgC4kSce9qzmmeHvJPqvM2gWC7_x2bcO_4IppKMaTcyY9uCpxN4iu6vdWVw7WkATjRpFv_9794enXDlCmyT45mU_Vg6r7bZ735AcX-UQCFA0eHi1g_j0w53tnWS8QSTC0ud87lKFFhlZabGtII4dVx4O8InYLWX2Bls36XDoHYmbxuNVHUJ1ZTVZz2Y7aRVojYsqTLE6UlFQoAGgJ_28yM-_XGJ5nx4eI4qaRba_e1Tk7sSW3hqf8M6QC5m6Fou3zEgzJ2iNRVfjAR37-ZKj3dQ8rqHPDcVC2SNcf5MKb9ZHzEXFCH7xpkXAYjfASRkmprb9ym2HTFu-8hfccacJwC8idQ9bBdzIR1xMH4MQS5l0jz55qylAa7fnO232zH9MOAgwpPuwfDtjfiTLD7bWdLOWdwe4AuGux0qt9B1dLyCEDs6-DyRQ0WbDzEG2T3Abty-PPqwkdx0VN5iz01SdiTa-9Z0E8pp6atl-YJJThs8zdSwwt1lxOZhhboxqCp1Q3GMildYrscWJuS6xAXYzNf-RSxd1PCc7aWgjCdJjZmGLeF7aRzRIawq6ht0WzsUQ2lblpiLnuDiVqOc7yZ-m_7cPkRYHR2pUPTUqx7yVjDx8V0OegmVjdz4h_utJHpZg28WUzXFAz1dnBWfujtXhYL_vVfFzIe94b2OqbxjOxQKs-V1MdPfAr7io8wWlBS3hV_-S0Nyh-D-oUcjOT-c_eNUK1klYiDlY-n-0yoGlKDOr52lI7BFXauakgBiFP-BDUA5zFOMKVWe_uQpJCEvqPluTjHQrt5mJheW2bNenJ36vHZ0JD5iD2kyJs8cMJFtsk1nxqJO0knENeNjokdiffoY-FBlh2cCDd8yPAQ90uvPxC0aK_MJiIeUMmZpMm7mGG7lrRPPoKE_Zrdm19QuNku6a9BVHquDaeV1Z4v0XDuLt1t3t1WhXzn3Xq40QeEN-3Fvu1K9qVyvWyFnvl7NS6_M1P69yIYErX_xFcUGL1bB_LXRXIY5iRGMfHCe43LxgvbNOWH5VRkywGlnapHcbg44d6nqqaENr2LBI5riwsEHIqU4Ke2FWbaZChKli-sq5vcpR6TipjuI9N1YzXz1nex0SJbkMlcYUgXmtHho7Q044FkjW5i4zfU1NIkN1bA7m7OeTO0duaH5n-HthlyjrzhqQrsPu7Aq2n4RRuETpcGsZ5V-8_Tunnz5kiO7sFuLZbBMnvp8Qsw4xalFJX9vj8sTmDRK767_-p-YkI96b1NSejsePruXH8eK3EZ8RuJeAt_k9ezcht1G2t6Cg1X8r8KWzihcwSh38eWjHYBt8UWEGB77VB6SiBreRUNMrmoNkAjceFLK0QOeysyGpZcO_w1-Ia-hJFourGQ53b2N9JJab-Ced4UosG1u3Dmoj8PBijAmoQEK7Xe9Nw5ChW8N3DMC9v1eGieyL9x39uV-x1OJ9-bv4L9CHsHcSn1gtYK1psgzegLFFUPAE05-a1YWgLRuPqN2ejtEC4GSDDCmXRczR7tv_GAU9jt_c88qUNqAG8EGm06IzHlRN6biVJWRJShwcGL8swoNVzi0VtSHSFrXJ2biRm6IppDHTHNJEAtB-1-WlwGuWRhmd3OcC8CDHMd9grWnqux-vA84rudLhkwNYgM2BPL0HbDaVilBaO0QymEsUCdJUB_gb0YThvYGGaetIg3d-6_H0zq5dA8YE6JxDA1Uu527vG2_CkWryyRXXb1Sj9ewZd_B7jMo40Wd0g7dnQj7fZl-Gi7Rcf"
          }
        },
        "stack": [
          {
            "fileName": "https://www.mercadolibre.com.ar/?skipInApp=true",
            "source": "ThirdPartyTracker RequestHandler"
          }
        ],
        "type": "TrackingRequest",
        "url": "https://print1.mercadoclics.com/display/prints/MLA/count?d=wFUQPrJjQfwHCp9brC6qr6wwcy6FuEm1pP9cn1rSmEWielVuHSJrTToutpQkxwuXrlGmV8qg3myf3XIOTJYewag_4nI6mnx2uMaNiVXWliOxi3EMe0oLeN-Bj3IH-PkGM48igINhcGQgZWhvFAQxEscc-33dUFnn4RsgjKBtFkpIpBwi8NfigvbfnZnG_3FcZG0gwoUK1ZqLpF8rkRxevGLlv1g9Ob7Laap0NygVsdbupd0SZaKBHO3sBP1736lg4-_btrAY_2E_W94aP5OO2AITZuWkUxlize4dxieufcRUOfUtDFS5Q3vI3sTzOoTeYOWsbHJl6_SlSWetpE_BDiosu0jSVJKHrcuJbNjv1JxjmlqQZuh3HMibUVzzdzkzDeMKswXKf5eZoW0zPvf8N9z3V_ec6vSZhv2bCin_GN36BUoGVGg5fY5_cEql03atumRBXZ2IBbbjTCTGZoAHYzV2i-4wXI-cyvYPOuudhbcz4VX-RF2TlvcnN1j3zK5fs2-bdD-fEThFGLEVmwEHOQSjAQ5luq6uTUjukry66WZVtVVC6Vc6YbF_nzA17yJOzZyhh1_k7CMIhthOF_m13uy1y3W5BccLOGsQwmr1HKN0Q2lC68nk8ZGMsqXIZONlOK_vjrnyItX6ZKaKuuueDvJnij1xF3eQaxMbOirvVqeUFEZ2YdA8Vf6i-kSQ-2nsAI9VT1duUNbkHH0FhL78DQCIciIrSc-gUyfUFNlVWM22Nn50duQgL41Zp2NPeelOYZF4ysAp5Opv3gOXWFX4n0SO8g1mMfiIw4DSFxEeHTtxyHtpdEcOHolB3n9Lz22DOcwx9xTuUAVHvjFHzc03FZ8IDJ7YVESY7p7AIuaEpWzdYs0qryEcn-0deM5mbwGktoj-86a02QIlRZKlUQc-mNYOlWqd9EPGa766Z6T72a_Bjh2H0VNLAzmvqss6EaHQpr88p25dM3nmeh-dIciwCc3dfdO4kzzjaX833RZsv3uFCSxoCK7R-UwR_W02AaytORJlsMlD7KunWSIRUh2syAW4f-xOgC4kSce9qzmmeHvJPqvM2gWC7_x2bcO_4IppKMaTcyY9uCpxN4iu6vdWVw7WkATjRpFv_9794enXDlCmyT45mU_Vg6r7bZ735AcX-UQCFA0eHi1g_j0w53tnWS8QSTC0ud87lKFFhlZabGtII4dVx4O8InYLWX2Bls36XDoHYmbxuNVHUJ1ZTVZz2Y7aRVojYsqTLE6UlFQoAGgJ_28yM-_XGJ5nx4eI4qaRba_e1Tk7sSW3hqf8M6QC5m6Fou3zEgzJ2iNRVfjAR37-ZKj3dQ8rqHPDcVC2SNcf5MKb9ZHzEXFCH7xpkXAYjfASRkmprb9ym2HTFu-8hfccacJwC8idQ9bBdzIR1xMH4MQS5l0jz55qylAa7fnO232zH9MOAgwpPuwfDtjfiTLD7bWdLOWdwe4AuGux0qt9B1dLyCEDs6-DyRQ0WbDzEG2T3Abty-PPqwkdx0VN5iz01SdiTa-9Z0E8pp6atl-YJJThs8zdSwwt1lxOZhhboxqCp1Q3GMildYrscWJuS6xAXYzNf-RSxd1PCc7aWgjCdJjZmGLeF7aRzRIawq6ht0WzsUQ2lblpiLnuDiVqOc7yZ-m_7cPkRYHR2pUPTUqx7yVjDx8V0OegmVjdz4h_utJHpZg28WUzXFAz1dnBWfujtXhYL_vVfFzIe94b2OqbxjOxQKs-V1MdPfAr7io8wWlBS3hV_-S0Nyh-D-oUcjOT-c_eNUK1klYiDlY-n-0yoGlKDOr52lI7BFXauakgBiFP-BDUA5zFOMKVWe_uQpJCEvqPluTjHQrt5mJheW2bNenJ36vHZ0JD5iD2kyJs8cMJFtsk1nxqJO0knENeNjokdiffoY-FBlh2cCDd8yPAQ90uvPxC0aK_MJiIeUMmZpMm7mGG7lrRPPoKE_Zrdm19QuNku6a9BVHquDaeV1Z4v0XDuLt1t3t1WhXzn3Xq40QeEN-3Fvu1K9qVyvWyFnvl7NS6_M1P69yIYErX_xFcUGL1bB_LXRXIY5iRGMfHCe43LxgvbNOWH5VRkywGlnapHcbg44d6nqqaENr2LBI5riwsEHIqU4Ke2FWbaZChKli-sq5vcpR6TipjuI9N1YzXz1nex0SJbkMlcYUgXmtHho7Q044FkjW5i4zfU1NIkN1bA7m7OeTO0duaH5n-HthlyjrzhqQrsPu7Aq2n4RRuETpcGsZ5V-8_Tunnz5kiO7sFuLZbBMnvp8Qsw4xalFJX9vj8sTmDRK767_-p-YkI96b1NSejsePruXH8eK3EZ8RuJeAt_k9ezcht1G2t6Cg1X8r8KWzihcwSh38eWjHYBt8UWEGB77VB6SiBreRUNMrmoNkAjceFLK0QOeysyGpZcO_w1-Ia-hJFourGQ53b2N9JJab-Ced4UosG1u3Dmoj8PBijAmoQEK7Xe9Nw5ChW8N3DMC9v1eGieyL9x39uV-x1OJ9-bv4L9CHsHcSn1gtYK1psgzegLFFUPAE05-a1YWgLRuPqN2ejtEC4GSDDCmXRczR7tv_GAU9jt_c88qUNqAG8EGm06IzHlRN6biVJWRJShwcGL8swoNVzi0VtSHSFrXJ2biRm6IppDHTHNJEAtB-1-WlwGuWRhmd3OcC8CDHMd9grWnqux-vA84rudLhkwNYgM2BPL0HbDaVilBaO0QymEsUCdJUB_gb0YThvYGGaetIg3d-6_H0zq5dA8YE6JxDA1Uu527vG2_CkWryyRXXb1Sj9ewZd_B7jMo40Wd0g7dnQj7fZl-Gi7Rcf"
      },
      {
        "data": {
          "filter": "||mercadoclics.com^$third-party",
          "listName": "easyprivacy.txt",
          "query": {
            "d": "-d76duxIF50NETtzdzSGVaK3aQkgGLx_Zfc4AxigePs9Ptoa_racPqPgP9FJpy2T-VvNVTMqzNbvExSUQHHXemjkgJNB-yLlYTqXq-cZ-v4h4NtXKc_8Dtdm4L6KyIkrUBUgsDT9u6Yf7KoraiF8O1-UxS7ocLil_3_oMaUaH1c77qLRYz25QqiX-Wm0Xj0X_mJCn3o8z1B0T9cqB2DDFFrApjNvmNh-2FDjx_dv2u59y7Y-0U7HMW3ihp7FFYzayaDTyL_TbyFJBvi2rm7KNRFme-RPEv35HH9hk1LZgUYOy0-0LzzkDoXq1_5Z869fvJ0UojdvGp52O26hUuViJDHENvAxvQ-EayBiJ-OmNOXHsQhHY8nY_rbI8X9kJCUkJztO50L9zyTqYteK-uhsTxGOsE59zF1mN4YeZbA0BrFqNdHRreQs1ATEQQNTRkkslpt3c3IC78RlqqO5fRqKXAp7DnsIP2Gvhv2VzBWYqKicpUsklYxUBVgXkGyfB4ge2J7TiJZIVUOKc1CdJYwKZkmzi8cHMalEnhZfCNCOtKn_OMbbYyic45OQuJjYsh4YA3-og4AYjhCEYozpHrJCFYxi97GBR8rqzBwuKUjydi_lV3zPj2_a5psMbPzC9fSRYdCbS1uRagReJxmHfXBk3AtJi0G5hTcAzfRnXH8-ij9FVRcv99C_Rbv_RPVayZB2mm6TWv80MEc1UWoFxuaGY75Nn_ChysVoheyVGGZuKFiHVW29PxeC7ejpJzgTsnjA7i2Q21Q731wzxt6xrKgh9G4SfoAkUD9_lV36MGg4vVshQbE-aGApmKZ4b4fagyoDEwaicSw1DVi-YtKG6EZ8ke5sbcSdt3CXXOBQ4sQXDdWPAg-iIUvsClLYm-Pq-Iz3bT0fvtLkeyUxR1NKarz56LGEkzDgMxxjdJaBoGPM-2EVGi3H3QOzFSFojaQP_ucer8ghcmyICtqZvOG82aY_dZLj6oPqM4SUQI2aMMeEDz1YnS732NxHnEO6l1Wcmg5bg22AYkKZdz1AJUmjqObvAEoSlW-9RFTq4JwVbeIOMrjar5lUwJDA1Lyju1Jm3DMjVBJDITOC9KbMvsXbeELkrvMROqCRW7ohzjCM9XEJwEPwTJhdwOpv8Qth9TiDconQptxgY2enkE97p0Stam5cLV286KeK0IVCTk3FeCuaLH78GZHfk0y_AFtdty2VD_T6xkth-VrpuGKC-WOScdN2ZGSKsaU5ZUBNH26kvR45YWVgXX12odP-tBVzioBZBt40ahUD781Gs_0yRSroC4GYv--nldjxfmBo0HryKCbGPChyouA8mnslzzcwvrCPiA1NvXdRLCH2hl3RD5SrCgUCK_YJigIKSVKZir2QSxSBj4mWN1yuMKf68lgpZCjeIs4BSxOX9ltFsH3iVtplYQCB1h3UGOcGyhYQUrIK77V1RxvafE4Ab-v2iIIp_VbNPzFa0L5JPgCcMyN_H0pfkoEOTj6z-bZZRM6qHXiYGH8bzJOptkTb-40chlq2q06lqeBpGtYDAsl-tMOWoqow798EWMmNmOg_CY_vRXXjs3IqzWjVbe8CwU_AQeBiZonYXpL27cqgp96WTXHK0bgjYo4HbN_JbWAQVBiLmqT-3kwk4oZS6QnlZaV-7uy9aWgbe-RicJUdkY36w27PX4HbZUGzBj5quSL_LdLVyscVZl74PPsQTt-zv7ncIKZmJgpCaeKJQI3kzTuAIWT0d6QrRFGoD2FKnzYLJ0gQpJRNf1EVjZjrtkR2igaWDDrRxPFqyek1mIk2HEcbb6_oAn7lIrNS-rsRpXGCJVYhC8GD8vEmIpR4VfwGzgJGPgBcqGeILiXaXhASP2LqtqSPqGTiXcXKHD8X2ZZ4PmJrxAYo4b4mdLAFtuTk9Ds25t92LkyqhqeSfudv2ORj5cE3ic5NXc7ND7f5EXlLvisr5Tp6YekrlFGFr97W6qPhLzdlwdpHbFBczEO5w8vuZUIT1DexWggKM-Yc5pivXKI7to2jnxvY9IgndR4lmxC7ox9UzKaNvJ8hA7WAjUS_c70k2EiD3o7J7zM8-c2edMvpHEhv13Vh0KsC1VQLYBFiwXDxsaAgfzkFt5O6se5GXXhkGSUTU74ckxT_BVvon4WHynDSkaZv0bBPoGVjLFV-zDzaISsSnNETXvCquz8C20pggFaQTaKmt_DW4H0lhsLZsJtguA7nyrbYpRO8H3rEg1s8-HVHHIkcVDAlNkHyujgvKXT16RI65RtI4tgFhr_b8jA_rBX77a1UD3IU1EKJ4EpllZ6qxgl3282Gq4MAmLoq2YMuE00MF-lU_Bj3qQosOnkF1aFT9iZSbxBvZaTeuHZr-nIkCGet_fwTBqD-QN6posKOq1bjXVzdI5Brs03D2vTnWTVOXD_UApCv6s3FjUUEAjLP9KLcMLlixPcZOw9BjK_WFrRe0hDR-rugIu3nW-JR7Yr1KsGoxU2y6UaoTTmdQZ7J5Eepiq5G1__lN885hFrmy7V2k2NV5_FTtNY9CrzZprjpfmepbJkX-IF5J1IHJaciK9ia5M0tRDlGgKSbfXXj4nZUWiw18jEpNe-yyLos3I3qwV3aVp1ORzMZuijKl-GgtS9GD8hh-PaT8kQ3o06I8sq0rmrJKYeHCQ5emIqwlLp_naTeW7M4FFZ3oHoZh5ZmImHNN1Lntgg2wJ7w1ZZsVwU3zqhCmOF3vXfz6H4jRTCNbQal1gK3MDU7yELdWjfwyHzR-vJ_8CNjVE_GA7mlacsQ7cPLRIJuK1zeHJPHz2vt"
          }
        },
        "stack": [
          {
            "fileName": "https://www.mercadolibre.com.ar/?skipInApp=true",
            "source": "ThirdPartyTracker RequestHandler"
          }
        ],
        "type": "TrackingRequest",
        "url": "https://print1.mercadoclics.com/display/prints/MLA/count?d=-d76duxIF50NETtzdzSGVaK3aQkgGLx_Zfc4AxigePs9Ptoa_racPqPgP9FJpy2T-VvNVTMqzNbvExSUQHHXemjkgJNB-yLlYTqXq-cZ-v4h4NtXKc_8Dtdm4L6KyIkrUBUgsDT9u6Yf7KoraiF8O1-UxS7ocLil_3_oMaUaH1c77qLRYz25QqiX-Wm0Xj0X_mJCn3o8z1B0T9cqB2DDFFrApjNvmNh-2FDjx_dv2u59y7Y-0U7HMW3ihp7FFYzayaDTyL_TbyFJBvi2rm7KNRFme-RPEv35HH9hk1LZgUYOy0-0LzzkDoXq1_5Z869fvJ0UojdvGp52O26hUuViJDHENvAxvQ-EayBiJ-OmNOXHsQhHY8nY_rbI8X9kJCUkJztO50L9zyTqYteK-uhsTxGOsE59zF1mN4YeZbA0BrFqNdHRreQs1ATEQQNTRkkslpt3c3IC78RlqqO5fRqKXAp7DnsIP2Gvhv2VzBWYqKicpUsklYxUBVgXkGyfB4ge2J7TiJZIVUOKc1CdJYwKZkmzi8cHMalEnhZfCNCOtKn_OMbbYyic45OQuJjYsh4YA3-og4AYjhCEYozpHrJCFYxi97GBR8rqzBwuKUjydi_lV3zPj2_a5psMbPzC9fSRYdCbS1uRagReJxmHfXBk3AtJi0G5hTcAzfRnXH8-ij9FVRcv99C_Rbv_RPVayZB2mm6TWv80MEc1UWoFxuaGY75Nn_ChysVoheyVGGZuKFiHVW29PxeC7ejpJzgTsnjA7i2Q21Q731wzxt6xrKgh9G4SfoAkUD9_lV36MGg4vVshQbE-aGApmKZ4b4fagyoDEwaicSw1DVi-YtKG6EZ8ke5sbcSdt3CXXOBQ4sQXDdWPAg-iIUvsClLYm-Pq-Iz3bT0fvtLkeyUxR1NKarz56LGEkzDgMxxjdJaBoGPM-2EVGi3H3QOzFSFojaQP_ucer8ghcmyICtqZvOG82aY_dZLj6oPqM4SUQI2aMMeEDz1YnS732NxHnEO6l1Wcmg5bg22AYkKZdz1AJUmjqObvAEoSlW-9RFTq4JwVbeIOMrjar5lUwJDA1Lyju1Jm3DMjVBJDITOC9KbMvsXbeELkrvMROqCRW7ohzjCM9XEJwEPwTJhdwOpv8Qth9TiDconQptxgY2enkE97p0Stam5cLV286KeK0IVCTk3FeCuaLH78GZHfk0y_AFtdty2VD_T6xkth-VrpuGKC-WOScdN2ZGSKsaU5ZUBNH26kvR45YWVgXX12odP-tBVzioBZBt40ahUD781Gs_0yRSroC4GYv--nldjxfmBo0HryKCbGPChyouA8mnslzzcwvrCPiA1NvXdRLCH2hl3RD5SrCgUCK_YJigIKSVKZir2QSxSBj4mWN1yuMKf68lgpZCjeIs4BSxOX9ltFsH3iVtplYQCB1h3UGOcGyhYQUrIK77V1RxvafE4Ab-v2iIIp_VbNPzFa0L5JPgCcMyN_H0pfkoEOTj6z-bZZRM6qHXiYGH8bzJOptkTb-40chlq2q06lqeBpGtYDAsl-tMOWoqow798EWMmNmOg_CY_vRXXjs3IqzWjVbe8CwU_AQeBiZonYXpL27cqgp96WTXHK0bgjYo4HbN_JbWAQVBiLmqT-3kwk4oZS6QnlZaV-7uy9aWgbe-RicJUdkY36w27PX4HbZUGzBj5quSL_LdLVyscVZl74PPsQTt-zv7ncIKZmJgpCaeKJQI3kzTuAIWT0d6QrRFGoD2FKnzYLJ0gQpJRNf1EVjZjrtkR2igaWDDrRxPFqyek1mIk2HEcbb6_oAn7lIrNS-rsRpXGCJVYhC8GD8vEmIpR4VfwGzgJGPgBcqGeILiXaXhASP2LqtqSPqGTiXcXKHD8X2ZZ4PmJrxAYo4b4mdLAFtuTk9Ds25t92LkyqhqeSfudv2ORj5cE3ic5NXc7ND7f5EXlLvisr5Tp6YekrlFGFr97W6qPhLzdlwdpHbFBczEO5w8vuZUIT1DexWggKM-Yc5pivXKI7to2jnxvY9IgndR4lmxC7ox9UzKaNvJ8hA7WAjUS_c70k2EiD3o7J7zM8-c2edMvpHEhv13Vh0KsC1VQLYBFiwXDxsaAgfzkFt5O6se5GXXhkGSUTU74ckxT_BVvon4WHynDSkaZv0bBPoGVjLFV-zDzaISsSnNETXvCquz8C20pggFaQTaKmt_DW4H0lhsLZsJtguA7nyrbYpRO8H3rEg1s8-HVHHIkcVDAlNkHyujgvKXT16RI65RtI4tgFhr_b8jA_rBX77a1UD3IU1EKJ4EpllZ6qxgl3282Gq4MAmLoq2YMuE00MF-lU_Bj3qQosOnkF1aFT9iZSbxBvZaTeuHZr-nIkCGet_fwTBqD-QN6posKOq1bjXVzdI5Brs03D2vTnWTVOXD_UApCv6s3FjUUEAjLP9KLcMLlixPcZOw9BjK_WFrRe0hDR-rugIu3nW-JR7Yr1KsGoxU2y6UaoTTmdQZ7J5Eepiq5G1__lN885hFrmy7V2k2NV5_FTtNY9CrzZprjpfmepbJkX-IF5J1IHJaciK9ia5M0tRDlGgKSbfXXj4nZUWiw18jEpNe-yyLos3I3qwV3aVp1ORzMZuijKl-GgtS9GD8hh-PaT8kQ3o06I8sq0rmrJKYeHCQ5emIqwlLp_naTeW7M4FFZ3oHoZh5ZmImHNN1Lntgg2wJ7w1ZZsVwU3zqhCmOF3vXfz6H4jRTCNbQal1gK3MDU7yELdWjfwyHzR-vJ_8CNjVE_GA7mlacsQ7cPLRIJuK1zeHJPHz2vt"
      },
      {
        "data": {
          "filter": "||mercadoclics.com^$third-party",
          "listName": "easyprivacy.txt",
          "query": {
            "d": "rDdVsxNjHejLNQCLqDM1mOtjiQDFs5tNJ7KI1xRSQg0psiHCD5eQcGJn9y1xekxjXgM-Xk3cvhukwqz3L92-m41Sft5YCb6vnKIGq9U9Xir5XhybgxfCXNFx-iuh3RJyBmMMifxwkcVosl0nGSsDiih_rVbHBLm_ql0cJNC0zpXpViTstLDZSQHDkxlZo7_RF_zTJsEHDlBx393i3MHp1hBxyhTjpxYvlEnw3gDjpvJYfVNASDh92L97Mksg52qhVZQCgbEuiEb94IWZbj4N4voXrP7E3A7CE8L4zL_ZHL38zeAxWAk9BHGh_Ul_lM4jEhSB17UxSAVFqJEv7IULOD_1IdrTpJ2dNpMcCyQCFqGKJStrLDtw9MXxhHNQJnD8tglTgApMMSr1Ymoo7cRIIE9tTLs8QDAYq__rXhQuA4TZFwkv7-CGxKPQzT_UknwJkJQjnmOBGNj3kB-Rl2kDayOQutcfWFFiFPW_3VyDJH1NCEldK2Ld9NWBT36XinN-KQ543Ol05NH8gb2bLrKGR_aJ8bru0HDZEX0PkfyGY3BtSK4a-JRD70fr6rJBnHHxyHaG3jnfAAuR6jYW_Jd2dJ787ICRmMP5Ow4ZaYUJ2Ac_kdChxxIMEZ2Wld1zBlDVMHN4-kI8pXrqvWFTDZn-sgFUQ2pD_kKxICDgOgk3FKCUt2VUrRr5N9X3mtyhQIQxDjP0Gvk5brzqMkJOi9S3x2wZOqVv16ils8IqbQuShDmYugZ1RRZZk0gxmOMVXZQwMnn_4ZEqqvXl_rPyZbIqr75I2QGy_niW-6JpLmlP5c7Mg3ORHA38eieW0hw__7b8ltH5_izDJKRxwx2eRKd4xz9pGHsn4eN0eNNGP2UVcWYMqekSck0v517j1gDMQtw2B7w5Zh_PI_Iw-Fi8cpSzkVTCdHKMMTYc27QnyUUBeWVl1yt4QMYKtYrJvfm5TDgmNqDlMtiX30Xh_qItRjmTaD_2xSguHnbSLVJKWfQwAYBqOx0Z6lUN-SLO_TQJReFR3PXLrscMNxtvYdkrMSTIPCscSYbqGgo_sPrUyn1JANkrHu5cFw4qmU8wgcOV0vb_-RWPx6a21Ef4sA_cmWQpHjDf9aUb9FrCRbM6xKQVXS7kNsDMQDWyO2Xu6oMz0dtL2qy0g2xClNd1YC_nJXtzp3w-4USOAJU8YLh_lYo0IMXEneR7wstv_IGs5yVJoQLWoWYsoZ8EI_RB0-QmtkoESJMy7ktqOiwhrRPfHjfptqSRNTUoS_C9iSF-lK90-Ovw8avIs6Nwb1XK3CIy1tr9IzDu2OLklgzSd-u_4oo5L-_m1RK9y1Y9pUpXG6okjp7Wxw74wL-GKWMDchSmV1kcXBLPE4FetWWVryNFlaS7kTLTraPbrzRQn2J-pXeu23ZmDUIYV_n3iySUNJzMb9hZmhfnLkUG5XxFRkjPcl6SujHxgHzpChggfksx0qtRnnUGh7slsu_x5ySuzy1Jc8VW7bM51O9k4AZxisZnsKVSzF9QDEUs0BTyTqGcA6tnTuSlbQYxVN7fzRFiB-BAhzgD6h4Rig0dgAdP9FSlG_DHSOII2l-cqHuTb9qoHJlXzCAaZeKNFrNvWeD6VBmL1Y8Ta6QcXAlkgsRlPG_JUBjlOmHlDql1mt3BkG-vVNMkVQlG8OSQIfOiGQPr0KMO9Ub_kUnEZQBny5AC63aBExqLuRv8dhmvRbYyers4cZMxGj0PDeL6LPIFyfjGiS4FZ9L98p1js3RsRt7i6lXF0-skw_lOid8oJZqKSWJFV62aoX0_NYwu-1XY60K1Ii6-aDyE9n1knWnVblXuFFLNezGDarVJnPsG3IjROXxp0n30OvxFwIqy6985bqAZ9q1DiMDmTTl041H150FLUbXSwfhFgXznMEMZ1V5kU2RULIqLl8sqREWGrvbmNCW9luow7gPYwmZ7Ay-Yp663y3sgGfC8SkHgahsaMREvdhM4KizBOBC2NJ_BJASrBPC-g83VeRSjPZKh0AFfao6WCDwqSFsCgQ3oUlECnhXtbAo8tRsUjVLCfWyyFe5lgpJSZF-A26XIk6bo-oonzW9q3QwNTpeK4aZL9d7b7WF_DEVWSm_7J1hpowBqhrv73xZ1FAhYVe_9pgBxI_9y0JjA6l3ynCqCDDXW71Doiddcl0vqH4tjQRrhRERlRwKI3hHAK9aiS5Q_s4KATM9BNuQDc8uHBAtNpKod57bSHXDgmA_y7ZX4k63BOX61b2S8NgaJCWAHmq1BhOAyKqTkF7Oed8WBNMd6d87koS2Q0N0p53zxA-pI8i1RViZGCV7-smpqJS_p4U8s5pbQ3hlKE5MEaqJLPDkFvuDMjA8VTgSZXdtddZ82FgZYa2AH5bcuajA0b59W3MrabxTNixsDyDoB_qE18P7o1R4L4bY8xvDD8bb29L9WMO8T25MHL2zfrItYcd-eSolpi0izdtCOK0SY0kOjkcJvQksWFSchcmTSpycueacOnv6Sik5aOzNf6fZjR53xbP3Y5NLJXAdEbr-WeLMQKrfjm4Z5ykn8IYGjv5-556z-4G_A2mRQJQHxh8lEgAl2egFS_5vaC1uBotSmonEcO3ymuIvEJtQvb62Gs65D_WahxqFgJY9f7Z2Wh1xfx8XRNleHVNHHWbLTPglQeT88-46AJVD3jULx1pHb6VAYAT8b2krBOQFbsQhKwCTJUsiyg_d2AZMTJ1JGbsVdd0gcwTxIjVY3fHsKea54D7y_8GFbFP7a1XwXDcYvNna5FXrGLEhCErDWAA"
          }
        },
        "stack": [
          {
            "fileName": "https://www.mercadolibre.com.ar/?skipInApp=true",
            "source": "ThirdPartyTracker RequestHandler"
          }
        ],
        "type": "TrackingRequest",
        "url": "https://print1.mercadoclics.com/display/prints/MLA/count?d=rDdVsxNjHejLNQCLqDM1mOtjiQDFs5tNJ7KI1xRSQg0psiHCD5eQcGJn9y1xekxjXgM-Xk3cvhukwqz3L92-m41Sft5YCb6vnKIGq9U9Xir5XhybgxfCXNFx-iuh3RJyBmMMifxwkcVosl0nGSsDiih_rVbHBLm_ql0cJNC0zpXpViTstLDZSQHDkxlZo7_RF_zTJsEHDlBx393i3MHp1hBxyhTjpxYvlEnw3gDjpvJYfVNASDh92L97Mksg52qhVZQCgbEuiEb94IWZbj4N4voXrP7E3A7CE8L4zL_ZHL38zeAxWAk9BHGh_Ul_lM4jEhSB17UxSAVFqJEv7IULOD_1IdrTpJ2dNpMcCyQCFqGKJStrLDtw9MXxhHNQJnD8tglTgApMMSr1Ymoo7cRIIE9tTLs8QDAYq__rXhQuA4TZFwkv7-CGxKPQzT_UknwJkJQjnmOBGNj3kB-Rl2kDayOQutcfWFFiFPW_3VyDJH1NCEldK2Ld9NWBT36XinN-KQ543Ol05NH8gb2bLrKGR_aJ8bru0HDZEX0PkfyGY3BtSK4a-JRD70fr6rJBnHHxyHaG3jnfAAuR6jYW_Jd2dJ787ICRmMP5Ow4ZaYUJ2Ac_kdChxxIMEZ2Wld1zBlDVMHN4-kI8pXrqvWFTDZn-sgFUQ2pD_kKxICDgOgk3FKCUt2VUrRr5N9X3mtyhQIQxDjP0Gvk5brzqMkJOi9S3x2wZOqVv16ils8IqbQuShDmYugZ1RRZZk0gxmOMVXZQwMnn_4ZEqqvXl_rPyZbIqr75I2QGy_niW-6JpLmlP5c7Mg3ORHA38eieW0hw__7b8ltH5_izDJKRxwx2eRKd4xz9pGHsn4eN0eNNGP2UVcWYMqekSck0v517j1gDMQtw2B7w5Zh_PI_Iw-Fi8cpSzkVTCdHKMMTYc27QnyUUBeWVl1yt4QMYKtYrJvfm5TDgmNqDlMtiX30Xh_qItRjmTaD_2xSguHnbSLVJKWfQwAYBqOx0Z6lUN-SLO_TQJReFR3PXLrscMNxtvYdkrMSTIPCscSYbqGgo_sPrUyn1JANkrHu5cFw4qmU8wgcOV0vb_-RWPx6a21Ef4sA_cmWQpHjDf9aUb9FrCRbM6xKQVXS7kNsDMQDWyO2Xu6oMz0dtL2qy0g2xClNd1YC_nJXtzp3w-4USOAJU8YLh_lYo0IMXEneR7wstv_IGs5yVJoQLWoWYsoZ8EI_RB0-QmtkoESJMy7ktqOiwhrRPfHjfptqSRNTUoS_C9iSF-lK90-Ovw8avIs6Nwb1XK3CIy1tr9IzDu2OLklgzSd-u_4oo5L-_m1RK9y1Y9pUpXG6okjp7Wxw74wL-GKWMDchSmV1kcXBLPE4FetWWVryNFlaS7kTLTraPbrzRQn2J-pXeu23ZmDUIYV_n3iySUNJzMb9hZmhfnLkUG5XxFRkjPcl6SujHxgHzpChggfksx0qtRnnUGh7slsu_x5ySuzy1Jc8VW7bM51O9k4AZxisZnsKVSzF9QDEUs0BTyTqGcA6tnTuSlbQYxVN7fzRFiB-BAhzgD6h4Rig0dgAdP9FSlG_DHSOII2l-cqHuTb9qoHJlXzCAaZeKNFrNvWeD6VBmL1Y8Ta6QcXAlkgsRlPG_JUBjlOmHlDql1mt3BkG-vVNMkVQlG8OSQIfOiGQPr0KMO9Ub_kUnEZQBny5AC63aBExqLuRv8dhmvRbYyers4cZMxGj0PDeL6LPIFyfjGiS4FZ9L98p1js3RsRt7i6lXF0-skw_lOid8oJZqKSWJFV62aoX0_NYwu-1XY60K1Ii6-aDyE9n1knWnVblXuFFLNezGDarVJnPsG3IjROXxp0n30OvxFwIqy6985bqAZ9q1DiMDmTTl041H150FLUbXSwfhFgXznMEMZ1V5kU2RULIqLl8sqREWGrvbmNCW9luow7gPYwmZ7Ay-Yp663y3sgGfC8SkHgahsaMREvdhM4KizBOBC2NJ_BJASrBPC-g83VeRSjPZKh0AFfao6WCDwqSFsCgQ3oUlECnhXtbAo8tRsUjVLCfWyyFe5lgpJSZF-A26XIk6bo-oonzW9q3QwNTpeK4aZL9d7b7WF_DEVWSm_7J1hpowBqhrv73xZ1FAhYVe_9pgBxI_9y0JjA6l3ynCqCDDXW71Doiddcl0vqH4tjQRrhRERlRwKI3hHAK9aiS5Q_s4KATM9BNuQDc8uHBAtNpKod57bSHXDgmA_y7ZX4k63BOX61b2S8NgaJCWAHmq1BhOAyKqTkF7Oed8WBNMd6d87koS2Q0N0p53zxA-pI8i1RViZGCV7-smpqJS_p4U8s5pbQ3hlKE5MEaqJLPDkFvuDMjA8VTgSZXdtddZ82FgZYa2AH5bcuajA0b59W3MrabxTNixsDyDoB_qE18P7o1R4L4bY8xvDD8bb29L9WMO8T25MHL2zfrItYcd-eSolpi0izdtCOK0SY0kOjkcJvQksWFSchcmTSpycueacOnv6Sik5aOzNf6fZjR53xbP3Y5NLJXAdEbr-WeLMQKrfjm4Z5ykn8IYGjv5-556z-4G_A2mRQJQHxh8lEgAl2egFS_5vaC1uBotSmonEcO3ymuIvEJtQvb62Gs65D_WahxqFgJY9f7Z2Wh1xfx8XRNleHVNHHWbLTPglQeT88-46AJVD3jULx1pHb6VAYAT8b2krBOQFbsQhKwCTJUsiyg_d2AZMTJ1JGbsVdd0gcwTxIjVY3fHsKea54D7y_8GFbFP7a1XwXDcYvNna5FXrGLEhCErDWAA"
      },
      {
        "data": {
          "filter": "||mercadoclics.com^$third-party",
          "listName": "easyprivacy.txt",
          "query": {
            "d": "w8MwR5PZ3QyUwq4ZMKNxWD4UsNDd5038oCekgioSkH_I6dr4q8DqwyTFu84xtdaaM5BPZeUwjYh1x2jDyUiZYGnQekaqgvMpZ3LlUbcFoGrIBekcQ76i63sOnZ9GCblPwq_WoO2pD3ebHzgJEnoZxQH_eLgH88xIILlvUo-BzVbYI5KCM85IzQvdU-ojbMM84zlbfjp2mTRK_ACYvDa6kLVrxajXfO42K9vVzfnLhiyAzEAr2Ps5130VmLchCgKbVCOBucYghNBykSYrqRdfTt9FSZo6-Rd7qBUSaGkwGu3sN1H-NPxASqdiCuoFyrrVxJsTvQf65sESjJqJk8bQEisLh7bxnwH5vmehQ3O8fvFq7-dZOSHYYkTkaj89cCMY4XZu8l_D7qURxJ-BEQC_tbNKcvtue7hrFhjOq0rnUcMIzxQKapIZ9yRVuE4YQzEvIR3TLRjX3fuTauCDpI0SVvoa4prPzbAZYbYMpZHdtYtugWFC7ZdW1kZsqSlJt9r45vlgvKsjzcN7AryabUntfP8HXSFZ623UbUgKPNF9VTG03P2uJI__p8xFV08HVkADuX2UxCxheX9R2RAobpnBk60yg3JytGqYDWbxRWVgic_nKFMx-oKL7_NxQFduYoYk0kotZdIKvSvHrZrYPszeUZ1k7KbecP-DRcacb5gtQIINV-gnPPkbDiFT6gXNLjMGe85nb2uGV57xrNE-58rYy1GkqO31FKYUhHD-sfCUTt28e_oJHkgJdsHdVi203HyrMJGThzH_OrJaRWKqHOW0dZra7QkXzj53l66P1zLI5n-_huL3DAXLe1XOUItaGWYWdj_-6lnbDYW2rEP9cmGwWYS1LGzXcBcCl2PyYUQgj3-xBesnWw6Sk4DvM2ODIy5lpWFUl2HiNTRpx_GbEi3yE_bOn3i3qFoawwQtXVIV5eQ_fB3xexnefR1gyS1AcyAonEuETnzoQXleeAR5YFw5bUSivJd4XxnJP3ULyHvf4JkUwDfJ0WebiXCQINvAL3Udz3MD83ZxEj0qZialRelxGG-riABrQR1zqIbqXM8X8clg64V9VzVjSIAHs9q9_QlR2yLg7R4UAanGYwsOenmXepkT0iOIcc527CZcNt2xoUm2LIjmMj7354AlwKVyafmYxfMamyr-qYx5JVIh0oEM1HLVygo5aOTxMzSTvEj3ugEaR1-AyrMBBfA3wWeaLHADaNtQFaGhdwjpzfAKtg8htC63DwTR8bfBPm-C1IXbenMcCp3eM9TVn-e2cR337xVt5LsDtJqZJJ8MomPwvgkxq1s6RisPGnIHIhV6emi5krEZPG-LAqeAnNGnnUiHnaoAypf6079HA1xIMUoniZCy1izXvHg9lwOuyG8KbigJL0Yp778WZUbK57i5hHPjJoh8lKkuM6YRqW57VU7zyfi7M9mhXBunqb99vAjYHC6awntZjwEMfyOZxbeeDsdeaJV3P3uq1NyEtUQgODtguyHlDddqYVT2bvGiHxj62RgjfnDqyReAzQBkj-5Zc7dRNRu0sb_HpJt3DnCHyGeWcwBF9g_ogVEB9pmbTwlB9eA1rCzBGzblJe_5e9CtvnyIHSL3mP_z_EA96QeiN4odjDjGpwOajGR-uE78pCEkE6z35dsWrooVxZ5lSwF0OMzYYCSpDuaSqb-lnugpo7_U49m1bhGwxX3PvfCe4469L4ow5NAze5wiDn6W3uVuvMapCZPd4uwcaYsFLlsKmm8zZib7eoYX-4nG359uBlgq87LFuweRHtbMBgWbISH_Zh9k1SJT9i-43U2M717wVaziNNtw8GXw0rh7FhyRygy-KPUsE8AykvJg08VAbzNdUYbA9bUekqZShEKAsn2sP6uwNunZfdou3gimhkVEiBn_NiOV-5-Oz5v60Q30Ll2gx_VrYfbGhXgUjCQ4AHn1ElCGqI3ywy47-H-Pp3VPt7IpCCZ3JH3dXQJcOW8f4-AKf_bDVloUZ8P3z_240SiEPKhY4o1LsF7xA6o2f8qVjbGZrjWvrGzLXUaRNu-k0TKaeZSgRxJSbe4U6aF56RT3fkjETZsC4piMmHw3dPoKqCrygd_AYIKS_XINrP97okvoxYfWb7cyn3XjPvCVEp0SjUNmBwq_BZjs-4RABV3gjPS2VRwYHyY5LuczwsHdRktpIlWYDcfTtMJT84ki4P38M3QKkocWWCXRmYELXc4R6LWWypn6TizUoGv_x4Hmf9yfyzHFtSVfo59SmBNTeCdy2eMaiwye3cIYxmW2YPxqiwltyqmb2IZYscKZKpXe7TPEpfULdeREJKTepkw2W455BU3_frv3f6HzU1j6gUF0nGCL0Qp59b4lmTDXzr_huBsEFSLx-cyeTguu8zLvCiOkDTKEwOyfvjOG0IbHDR1CiasFBvKjntCfW7fECgB6t4IwTiXrhVEH1uzBmYnSUFU3-HaQy7IUJiiw-a-uUDRmfe8-gjSRj66V99_F4qzkF6SCH-muEbsXzBc9P5Uv5LH01-bX2aBAbNOh7Ocpu-E5xtDfD2KaLAVlSBghE1B_z5L5E4MoCvfN5GL7fGcxmWiJDpyky9i8UIrBjVEJGX5aUd62H-ifinAPITLUk87Q0kpoktvYn6ZYzWXgN8mCZERWz39uIhO5AzyFCSFZUthIa-Ceqi8PUHA5W_rVLu2K2v3pnLbYI1cpM9JBIu0Ra27eGPJwOvApSn5MyeNFgC8Yc_lXNkfB3bE7-9_2zyaHdzcDiEwGnfTyBQ-JmuIty6cJo3O7CiL7XqPnATk"
          }
        },
        "stack": [
          {
            "fileName": "https://www.mercadolibre.com.ar/?skipInApp=true",
            "source": "ThirdPartyTracker RequestHandler"
          }
        ],
        "type": "TrackingRequest",
        "url": "https://print1.mercadoclics.com/display/prints/MLA/count?d=w8MwR5PZ3QyUwq4ZMKNxWD4UsNDd5038oCekgioSkH_I6dr4q8DqwyTFu84xtdaaM5BPZeUwjYh1x2jDyUiZYGnQekaqgvMpZ3LlUbcFoGrIBekcQ76i63sOnZ9GCblPwq_WoO2pD3ebHzgJEnoZxQH_eLgH88xIILlvUo-BzVbYI5KCM85IzQvdU-ojbMM84zlbfjp2mTRK_ACYvDa6kLVrxajXfO42K9vVzfnLhiyAzEAr2Ps5130VmLchCgKbVCOBucYghNBykSYrqRdfTt9FSZo6-Rd7qBUSaGkwGu3sN1H-NPxASqdiCuoFyrrVxJsTvQf65sESjJqJk8bQEisLh7bxnwH5vmehQ3O8fvFq7-dZOSHYYkTkaj89cCMY4XZu8l_D7qURxJ-BEQC_tbNKcvtue7hrFhjOq0rnUcMIzxQKapIZ9yRVuE4YQzEvIR3TLRjX3fuTauCDpI0SVvoa4prPzbAZYbYMpZHdtYtugWFC7ZdW1kZsqSlJt9r45vlgvKsjzcN7AryabUntfP8HXSFZ623UbUgKPNF9VTG03P2uJI__p8xFV08HVkADuX2UxCxheX9R2RAobpnBk60yg3JytGqYDWbxRWVgic_nKFMx-oKL7_NxQFduYoYk0kotZdIKvSvHrZrYPszeUZ1k7KbecP-DRcacb5gtQIINV-gnPPkbDiFT6gXNLjMGe85nb2uGV57xrNE-58rYy1GkqO31FKYUhHD-sfCUTt28e_oJHkgJdsHdVi203HyrMJGThzH_OrJaRWKqHOW0dZra7QkXzj53l66P1zLI5n-_huL3DAXLe1XOUItaGWYWdj_-6lnbDYW2rEP9cmGwWYS1LGzXcBcCl2PyYUQgj3-xBesnWw6Sk4DvM2ODIy5lpWFUl2HiNTRpx_GbEi3yE_bOn3i3qFoawwQtXVIV5eQ_fB3xexnefR1gyS1AcyAonEuETnzoQXleeAR5YFw5bUSivJd4XxnJP3ULyHvf4JkUwDfJ0WebiXCQINvAL3Udz3MD83ZxEj0qZialRelxGG-riABrQR1zqIbqXM8X8clg64V9VzVjSIAHs9q9_QlR2yLg7R4UAanGYwsOenmXepkT0iOIcc527CZcNt2xoUm2LIjmMj7354AlwKVyafmYxfMamyr-qYx5JVIh0oEM1HLVygo5aOTxMzSTvEj3ugEaR1-AyrMBBfA3wWeaLHADaNtQFaGhdwjpzfAKtg8htC63DwTR8bfBPm-C1IXbenMcCp3eM9TVn-e2cR337xVt5LsDtJqZJJ8MomPwvgkxq1s6RisPGnIHIhV6emi5krEZPG-LAqeAnNGnnUiHnaoAypf6079HA1xIMUoniZCy1izXvHg9lwOuyG8KbigJL0Yp778WZUbK57i5hHPjJoh8lKkuM6YRqW57VU7zyfi7M9mhXBunqb99vAjYHC6awntZjwEMfyOZxbeeDsdeaJV3P3uq1NyEtUQgODtguyHlDddqYVT2bvGiHxj62RgjfnDqyReAzQBkj-5Zc7dRNRu0sb_HpJt3DnCHyGeWcwBF9g_ogVEB9pmbTwlB9eA1rCzBGzblJe_5e9CtvnyIHSL3mP_z_EA96QeiN4odjDjGpwOajGR-uE78pCEkE6z35dsWrooVxZ5lSwF0OMzYYCSpDuaSqb-lnugpo7_U49m1bhGwxX3PvfCe4469L4ow5NAze5wiDn6W3uVuvMapCZPd4uwcaYsFLlsKmm8zZib7eoYX-4nG359uBlgq87LFuweRHtbMBgWbISH_Zh9k1SJT9i-43U2M717wVaziNNtw8GXw0rh7FhyRygy-KPUsE8AykvJg08VAbzNdUYbA9bUekqZShEKAsn2sP6uwNunZfdou3gimhkVEiBn_NiOV-5-Oz5v60Q30Ll2gx_VrYfbGhXgUjCQ4AHn1ElCGqI3ywy47-H-Pp3VPt7IpCCZ3JH3dXQJcOW8f4-AKf_bDVloUZ8P3z_240SiEPKhY4o1LsF7xA6o2f8qVjbGZrjWvrGzLXUaRNu-k0TKaeZSgRxJSbe4U6aF56RT3fkjETZsC4piMmHw3dPoKqCrygd_AYIKS_XINrP97okvoxYfWb7cyn3XjPvCVEp0SjUNmBwq_BZjs-4RABV3gjPS2VRwYHyY5LuczwsHdRktpIlWYDcfTtMJT84ki4P38M3QKkocWWCXRmYELXc4R6LWWypn6TizUoGv_x4Hmf9yfyzHFtSVfo59SmBNTeCdy2eMaiwye3cIYxmW2YPxqiwltyqmb2IZYscKZKpXe7TPEpfULdeREJKTepkw2W455BU3_frv3f6HzU1j6gUF0nGCL0Qp59b4lmTDXzr_huBsEFSLx-cyeTguu8zLvCiOkDTKEwOyfvjOG0IbHDR1CiasFBvKjntCfW7fECgB6t4IwTiXrhVEH1uzBmYnSUFU3-HaQy7IUJiiw-a-uUDRmfe8-gjSRj66V99_F4qzkF6SCH-muEbsXzBc9P5Uv5LH01-bX2aBAbNOh7Ocpu-E5xtDfD2KaLAVlSBghE1B_z5L5E4MoCvfN5GL7fGcxmWiJDpyky9i8UIrBjVEJGX5aUd62H-ifinAPITLUk87Q0kpoktvYn6ZYzWXgN8mCZERWz39uIhO5AzyFCSFZUthIa-Ceqi8PUHA5W_rVLu2K2v3pnLbYI1cpM9JBIu0Ra27eGPJwOvApSn5MyeNFgC8Yc_lXNkfB3bE7-9_2zyaHdzcDiEwGnfTyBQ-JmuIty6cJo3O7CiL7XqPnATk"
      },
      {
        "data": {
          "filter": "||mercadoclics.com^$third-party",
          "listName": "easyprivacy.txt",
          "query": {
            "d": "q0P20JAPNPpnkvZouDjU2u0MKXR0KwUXww2L0d2KT3XDRLQWkqc97nckTjHWCVZ3Qf9dgg7fBdd0PYec_R5685KbcgOkaAZ9PUcdhYjhxRBTzhqWXmgTKSiQMFZih5J6d7KBdqxpwftj3hPUbZesg1VMC9XoEBEmCNgjqnkzKVQ9-Y0V3yOM3z2mdXE0p1y0bsbYOsRuHITej0zs8C5r2YNWnvDwDOVE9vPt7WQ8CjL1nCHYNWTQ6nh4z5r4Ht5boqcfq65Uj69n_BNQKuF0llAEkhiEocDiqZ7oTu6GJ2Xec0SCmSYOsbMwegOBiHUEoZEK76XCxtNHir1OA83kL2W63L-lY2FoWMOsSe78WfZca8RzZiT4Vb-WevPgTlFNmsw_ccD1jRvvF77y8DOtNKXlN_1zMJct8BMHu-sJSuq_K_LzqDW50nZ35bspMtMu0cj2BsNjWeEOHIJbZsItw696a0a-TtDaNnqtXTin5RPMHKxL89ZsFBd0Rn48EL6Ih4L-lcqMVDitFVYtxzzLif8dygjrsa1n1uxMg-7CB7NzMANQalE4DMLKNuIbs-0DAj9jSp020qY9UMTFSmbTM1XXMuYns0Y9hwvTArwWl92vZahf0Dc67yav1xc9n0Ta0h0ks5BH8ddNXGI5obkqLXe62X37-aSizSqgAOrEReCwJWjur2z_eh8VmwqZBrGj0Vu4krHkgUinKsxDY_qg_8UTnxPUs8ZFw0RCS3Rx9ZyhFXOAGNqBvPPEGMQqhDrL5r0i0O006BmM-efoTIY0d9QnYVSXbOcnhFiWDW5oMZaKaoH7HNP6syrE2S-3DqHU3w19MlNwsRxDgWsJJG4kXngtRrliIqj-eAwhljEl7CfFFgtDCFxw7YTHDkv2ot8y3prFHdA08qleygHSmlH0xRgCpGyMlaMrEysmOIBp9Oa68nGMfddbczQyCIDak3SltmxTwH7BO6NuqDwmGKA0fzuDSVsZVKE0In16iDOv_Kd4QanwIl89WQU1qEwmWlBXWyqLyhzM2o6lWqWK889NODxO1O-dsI_RJz4UuTZhr4Zye2RLbF3kqDZ3KUQha0wcGhnvcEpsbm4MXMoXm_x0jU3UNLgEpv9WwsjfTZn1LKFAAohhcLl8nIUp7osgLHStd32weJDxm1k5LE2rl9Xt9yzqppwwwD6TStSh_lpF7R8ebd6aCdRHk4BxiAvK0BGdeSFKJv4rKI6Q0x-xfxEQkFGC1qQ0X33UMeRob8dhyZEDwwZN_exbPFYh3go1LANKZce5C-3BUhdltpArxTZw6-u7zTe7CFcd8U9CFbg0N9bTCe55SM6oUVnybhEnNtZyretaxZAimcXE1yTkixJ-m7iXprjMJTxggxevBiv8N3_iVa7Z0siR3nO7D6HOTuc-a3NgDFegExRRXgurxdORjgibGv7M6dBcTUIjqpq2l2tutdE4uFK5tvS8271e6w12SWaWgXRhO5MjtP_em1cPzzdb9bKwKt_UrNUdOr6nu6ZG9hAS7YmVQc8b-ACOVmcTKv2C-I6idujVFMNJxjYYhdggRGyF_QbGclqzAtZZke2-1k0U3_nf65HnKU1V-Ng5dok6HXxnJrovdSOQ4B5CxfTSSerGE6LsMzZJ_tDqd7eiY9wfPxOkAEwDLG8w9k3IRaxbnIdSZxKrGHaHAYbZr3nCBXlZoRVex4nn51skpHZqIzHB-zsi3dr_3dOTB53Eq96JuBAB5pXNn6L-kiBYF8-ZY9q75ybzWCYFk4gynHFVj2phgYp_irOEYd0NNVvmiRKOFpP0orPAr5KhRLa__PxfmW8r8mQx5LpE1oBk0LapzYmXwAZIVcQK5ZQEy8kpWVtJ8lzR-taTX0r33YfHXubBZuanPSGdt191CUqGBHsxp72Kq9RsWSTEfHh3lNE94j863WwYplCSHApMrdJdcE5LkJPVRAypfU5nveQrfyV9N5JVDI0kTmT2cqUG18QKlQ4xIzzkIao4V_802rCawj2iAmkupwf5DjQX58qYDFSzQiTdhZd0DK3bh-xTgxhakKWsYQJdSxXUiofEmi-hodpypGGxlJtJv83hc1fn3kSj-7zMmBrVdGGjIfkH6vOEDkni0fjhKIjsxHW6SnLfilDVsqGcemk4o3F08AN4cfm-CzcPUee3NKM9D96kZUuwjTOpgsrwK2e3fddTjxF40XtlRXPjzJ1ZfbhxtadSemWAZEQUWSQ9lyRvbD2ry7u9ube1BO_HBe94E1BXQkjxySJGt6CwkOG1HlS5kGtZvVu9yDw2klaPacpqshX-WFoFZw8AfNHRsuI-AyCr8kGsNjo0Lb5qETqE0ZLm11LgJW5yMvDb1QNFiuNfP9co7Uol2VzKYXO6IgupE0W1OS0AOGBBhYxanVkeVOAQMThH3y1Wd6vBXGIE0ehjnWp5un3ISO5bZm6qXEimM6mjgH4tF6T6K_Xay2L_syDRpYQ0-tvbhPLQkf51LM5S8R_ifd7vEW3Z09NYNZ_KGzt4lX4-P9VxpgJ7k6hp0HfK4wPMRzM1ewH3rHM7Ic-YuyJD6ueMmIEfp7pJkScLio3xT3jT2fVeOHGpW7N5TxqAJMAUsSX4tMgcsLXvMZjQWYqigF1WpyX-1YklgG6Ay8_tnRUOtPi1M8VMJ_X_H72u9aveZQNMSFMtl_NICl0FHuDKhFRvhWp3E31DIuoVP8UzEIOf8ltDsdJo99Ytf5gV6W9g8MfOFRVuYuvZ69-dUzyUp-5VxBBchKuul9FsG6ejShHvFJab6t7GjiVLSXom9Gaf"
          }
        },
        "stack": [
          {
            "fileName": "https://www.mercadolibre.com.ar/?skipInApp=true",
            "source": "ThirdPartyTracker RequestHandler"
          }
        ],
        "type": "TrackingRequest",
        "url": "https://print1.mercadoclics.com/display/prints/MLA/count?d=q0P20JAPNPpnkvZouDjU2u0MKXR0KwUXww2L0d2KT3XDRLQWkqc97nckTjHWCVZ3Qf9dgg7fBdd0PYec_R5685KbcgOkaAZ9PUcdhYjhxRBTzhqWXmgTKSiQMFZih5J6d7KBdqxpwftj3hPUbZesg1VMC9XoEBEmCNgjqnkzKVQ9-Y0V3yOM3z2mdXE0p1y0bsbYOsRuHITej0zs8C5r2YNWnvDwDOVE9vPt7WQ8CjL1nCHYNWTQ6nh4z5r4Ht5boqcfq65Uj69n_BNQKuF0llAEkhiEocDiqZ7oTu6GJ2Xec0SCmSYOsbMwegOBiHUEoZEK76XCxtNHir1OA83kL2W63L-lY2FoWMOsSe78WfZca8RzZiT4Vb-WevPgTlFNmsw_ccD1jRvvF77y8DOtNKXlN_1zMJct8BMHu-sJSuq_K_LzqDW50nZ35bspMtMu0cj2BsNjWeEOHIJbZsItw696a0a-TtDaNnqtXTin5RPMHKxL89ZsFBd0Rn48EL6Ih4L-lcqMVDitFVYtxzzLif8dygjrsa1n1uxMg-7CB7NzMANQalE4DMLKNuIbs-0DAj9jSp020qY9UMTFSmbTM1XXMuYns0Y9hwvTArwWl92vZahf0Dc67yav1xc9n0Ta0h0ks5BH8ddNXGI5obkqLXe62X37-aSizSqgAOrEReCwJWjur2z_eh8VmwqZBrGj0Vu4krHkgUinKsxDY_qg_8UTnxPUs8ZFw0RCS3Rx9ZyhFXOAGNqBvPPEGMQqhDrL5r0i0O006BmM-efoTIY0d9QnYVSXbOcnhFiWDW5oMZaKaoH7HNP6syrE2S-3DqHU3w19MlNwsRxDgWsJJG4kXngtRrliIqj-eAwhljEl7CfFFgtDCFxw7YTHDkv2ot8y3prFHdA08qleygHSmlH0xRgCpGyMlaMrEysmOIBp9Oa68nGMfddbczQyCIDak3SltmxTwH7BO6NuqDwmGKA0fzuDSVsZVKE0In16iDOv_Kd4QanwIl89WQU1qEwmWlBXWyqLyhzM2o6lWqWK889NODxO1O-dsI_RJz4UuTZhr4Zye2RLbF3kqDZ3KUQha0wcGhnvcEpsbm4MXMoXm_x0jU3UNLgEpv9WwsjfTZn1LKFAAohhcLl8nIUp7osgLHStd32weJDxm1k5LE2rl9Xt9yzqppwwwD6TStSh_lpF7R8ebd6aCdRHk4BxiAvK0BGdeSFKJv4rKI6Q0x-xfxEQkFGC1qQ0X33UMeRob8dhyZEDwwZN_exbPFYh3go1LANKZce5C-3BUhdltpArxTZw6-u7zTe7CFcd8U9CFbg0N9bTCe55SM6oUVnybhEnNtZyretaxZAimcXE1yTkixJ-m7iXprjMJTxggxevBiv8N3_iVa7Z0siR3nO7D6HOTuc-a3NgDFegExRRXgurxdORjgibGv7M6dBcTUIjqpq2l2tutdE4uFK5tvS8271e6w12SWaWgXRhO5MjtP_em1cPzzdb9bKwKt_UrNUdOr6nu6ZG9hAS7YmVQc8b-ACOVmcTKv2C-I6idujVFMNJxjYYhdggRGyF_QbGclqzAtZZke2-1k0U3_nf65HnKU1V-Ng5dok6HXxnJrovdSOQ4B5CxfTSSerGE6LsMzZJ_tDqd7eiY9wfPxOkAEwDLG8w9k3IRaxbnIdSZxKrGHaHAYbZr3nCBXlZoRVex4nn51skpHZqIzHB-zsi3dr_3dOTB53Eq96JuBAB5pXNn6L-kiBYF8-ZY9q75ybzWCYFk4gynHFVj2phgYp_irOEYd0NNVvmiRKOFpP0orPAr5KhRLa__PxfmW8r8mQx5LpE1oBk0LapzYmXwAZIVcQK5ZQEy8kpWVtJ8lzR-taTX0r33YfHXubBZuanPSGdt191CUqGBHsxp72Kq9RsWSTEfHh3lNE94j863WwYplCSHApMrdJdcE5LkJPVRAypfU5nveQrfyV9N5JVDI0kTmT2cqUG18QKlQ4xIzzkIao4V_802rCawj2iAmkupwf5DjQX58qYDFSzQiTdhZd0DK3bh-xTgxhakKWsYQJdSxXUiofEmi-hodpypGGxlJtJv83hc1fn3kSj-7zMmBrVdGGjIfkH6vOEDkni0fjhKIjsxHW6SnLfilDVsqGcemk4o3F08AN4cfm-CzcPUee3NKM9D96kZUuwjTOpgsrwK2e3fddTjxF40XtlRXPjzJ1ZfbhxtadSemWAZEQUWSQ9lyRvbD2ry7u9ube1BO_HBe94E1BXQkjxySJGt6CwkOG1HlS5kGtZvVu9yDw2klaPacpqshX-WFoFZw8AfNHRsuI-AyCr8kGsNjo0Lb5qETqE0ZLm11LgJW5yMvDb1QNFiuNfP9co7Uol2VzKYXO6IgupE0W1OS0AOGBBhYxanVkeVOAQMThH3y1Wd6vBXGIE0ehjnWp5un3ISO5bZm6qXEimM6mjgH4tF6T6K_Xay2L_syDRpYQ0-tvbhPLQkf51LM5S8R_ifd7vEW3Z09NYNZ_KGzt4lX4-P9VxpgJ7k6hp0HfK4wPMRzM1ewH3rHM7Ic-YuyJD6ueMmIEfp7pJkScLio3xT3jT2fVeOHGpW7N5TxqAJMAUsSX4tMgcsLXvMZjQWYqigF1WpyX-1YklgG6Ay8_tnRUOtPi1M8VMJ_X_H72u9aveZQNMSFMtl_NICl0FHuDKhFRvhWp3E31DIuoVP8UzEIOf8ltDsdJo99Ytf5gV6W9g8MfOFRVuYuvZ69-dUzyUp-5VxBBchKuul9FsG6ejShHvFJab6t7GjiVLSXom9Gaf"
      },
      {
        "data": {
          "filter": "||mercadoclics.com^$third-party",
          "listName": "easyprivacy.txt",
          "query": {
            "d": "YvxuF3CDJfLoYQhf2jzUjLwol6xrYqqsov_tMrGt4MbNfUHPnw-pyIPBbQQFbimMrMZNO5gbzyWN99zcpYZ5CGEUyFrg7vSDLsIMyWdFyt0V3ILM9uAaWFp8RPDHHcF3Mv1yOfevFaZJIP6MrOOT_P86al7rFcwrFH0eD1qRxl1j0C29ew42uhG4q6J_J2ABUE-d2uy4a11xzjazgFqNJJFtgKwMUcmk6QggSb2Z9naFOzWoP-ok22ol-GpSA63mRwvueV3B_6jThTAuAxbCfuliQKk6hUWC0Z3UpfOtUwQlKtyPZwqJehYx2cPSS379km5ONJlcp-EcxChon-CbOWFZdRvhP_OO2hJyIFoAlqd4m5FE_IEcZlHT1zoUropKuYncrWz-pZEWjH2Dw_-Ynh_-BdETrPUBAf2LArY3v80rAdOndtwc-lLO3fTzH4qto6-2mhTC0dlickPcUBQd4z14ksAW3paWNMuw7IL9O2NLfF3ATdT6k-1895muHjb3CA4eySlek8BippLspali24RajNER93b37PYmsL8iHqqnPvAK2dIKfP7AVKrnGKfMLMv-jswA1igEaqcCklIJ4V3AOFCUFlXcFz99EfHDQEq-Od47c-vkv3U-Oku4a8hhs3AwbTun-433kHmrKhVCf93FPmS9LDkN-2x8QOGySeg3SLEHxgbnZngl9CIYjs_jhfh7gfUPtpHWHkziRWmKW3h16BOUj79c8nsXSj6kKJlJbKs4qrNFGdcivcc4tFsbKjFu5Sl3H0wNF3AlS8EtVSQabfXocMkgxPJv4A5olhXdRSy2Cj11hJBpqKLAuQPKgZhvclkeiXzGISlQjDGuEm2TFhZIjPQWw0v3Z_C9onSfLtDIWOOUxbNDkeZeW3z045ptuwgJ-iz_tcRgYlrj5GeYB3vKhPdzsMfg081N0WX9gWAzdsO89CNi_7KHmYQXdnTDF1tQ2gdUCpIHU8JXuYb9mvGj8htmVkncQVIMtZn91yy2ui-xytjfTTSjktpTO7NF1PGehT1zS6zZd0p2tBSYPLI2akVGFuc3_Yy69zt-6-xvkSOmKYHy0A2cafbfQfxFIaP3EuIMXwRT2PcIPwdRHGYISbgpMEKMLlv_oyGxjs0-j71fAI44Qwd_-NI_5QV6hCr9DLpf4MGsw3_AOdnUTmBgDh8_-S4Ud1XAwIqY8uybaCOiKeE2ZKwgsJTtNQoW16ckx6NP5gIlg_10aullMBnd1-jAiGXPBTlu4VIFuvyzAKUwMI9m3YBLC1-p2kX1qXxqxAwfL6mLmyEMJLkcvgYLAeZKb4yxj8COdpGA_Zmwf59-9zdJVg9TooRVaX565TN7M2WMTDO8vPcuOxziVl_md2UuZ3JhH47RlTrYSMAR_qUSZVJ7Fswq3kzYMmA80HPMoLjqWcgyhpCmJzbMwx_yIzENt5FSlzigPk57hX_W1RuBzll1aVZy27Yet3lotby7DBK_lkGr8HoS5JiTPm0blN9A4Q7T0Ay-Y0niDQmz1n4PJohwgg5VKchgOyfx6hfv2kWgPrVaOaT446HCxPdd99EaZnoLl4stbkCeJVhe4zANj6mZMgWAwNXG_a-33ICnfVkmQUYmkimsvxtKZEHpxf24RqvqC_yRILA2gDUjybvTDW3f6aQlfdT6R_xEB2GK7wJtVloo3SRyWzGyfdDhm8ha2iy0up9Pg-8YaCSSyAgJwUz18UYQ9cQ-LN9c3aXFYbRVafE3Isf7w89RzBPLqDwuQvXHMODPQ3yduD2vdbYe4xWE-uUngaSFaPegFGW52G01SHIHvmV0jP_P4-LolT5Cf3SBpruHdV8PJKW7rLthYSh-32XUZEo94SrzJsaW2nRecm1NjGvGKAdWohQ0DcpAaqZYtI79E6y6Sj_nsL7_xe2-_chHBsx-Fb8Uvo3BTtbsSruj3okjiHvNPSoVSiF92uG5iWgUseUuxsvnrW0uuL-pGD_qWFlEumpr7FGAMGRoRDjYJwLnJZBo8xkch1jM6ztrcuXUPYMXcHF6eKNKEMa4ShGrnbowM0xVwKpxwSEgaHy1pKq0_MwoRDEvlvB3jICp7TxvjetTWzX7mFazX5Ji4jTQOdc4P9kl_2vnkBVwWShI_xlJiL-AMh5AJgm_2P45wEawy6V3AvXoGNpNfyoYxB-EcdUrekWDFJbwdF04V_VjML4k0sKhKR1QMsOkJg9C3FqjNBfLq7jQ3ANanQQCi9Zes1wp0_ymily8KRGDnSp2LgXX1LXGBQvUSk--g2ifXeIZfRXoFK20ID-A2CU6WuWcNi_kDR4HH5Iyxw2pSxi2TVelVKm9WNG1fbhoxbWJkhgtyhYdbVv_ry3P3h8yuk7Y-dDGEO_V9mAh9ape-qirMT0XoopCSTiXnoj1j_nim_qQCw7w5KEhcDtNXdbOUyzK_poWlSCcN-gDR4BCAvBRTXHGAU6dM9eqyR7cvBszyeBDAo2l3go3jBnBNHLEoksqLilYU5GPxUuobim0Xyw4LaEYWeCalTMSPAAX_qvHDwGu95wchIb_5khF_CtZ6wKEqiMD1gOFeWqNUJwl11AOil69NqUMxRvrh3lSJ9wYFWNX1h9OpeTESgsrTAovg99oGyzEGOlUs4K9lY8x4f_UAFWOwZwtO2bSDe7R9vFEwEEgQ__YRJGf-mzcREWk1I6in-arWipi7wNsuC54B41lr6W_fnDm8vPh3hNCWHVOocaIvNuztSY53ZR6W0agk4pNub7kl8xZPi5Dtj0F3tqVqZC4VU0vfK9MUqjYWyfo_lBfx2A"
          }
        },
        "stack": [
          {
            "fileName": "https://www.mercadolibre.com.ar/",
            "source": "ThirdPartyTracker RequestHandler"
          }
        ],
        "type": "TrackingRequest",
        "url": "https://print1.mercadoclics.com/display/prints/MLA/count?d=YvxuF3CDJfLoYQhf2jzUjLwol6xrYqqsov_tMrGt4MbNfUHPnw-pyIPBbQQFbimMrMZNO5gbzyWN99zcpYZ5CGEUyFrg7vSDLsIMyWdFyt0V3ILM9uAaWFp8RPDHHcF3Mv1yOfevFaZJIP6MrOOT_P86al7rFcwrFH0eD1qRxl1j0C29ew42uhG4q6J_J2ABUE-d2uy4a11xzjazgFqNJJFtgKwMUcmk6QggSb2Z9naFOzWoP-ok22ol-GpSA63mRwvueV3B_6jThTAuAxbCfuliQKk6hUWC0Z3UpfOtUwQlKtyPZwqJehYx2cPSS379km5ONJlcp-EcxChon-CbOWFZdRvhP_OO2hJyIFoAlqd4m5FE_IEcZlHT1zoUropKuYncrWz-pZEWjH2Dw_-Ynh_-BdETrPUBAf2LArY3v80rAdOndtwc-lLO3fTzH4qto6-2mhTC0dlickPcUBQd4z14ksAW3paWNMuw7IL9O2NLfF3ATdT6k-1895muHjb3CA4eySlek8BippLspali24RajNER93b37PYmsL8iHqqnPvAK2dIKfP7AVKrnGKfMLMv-jswA1igEaqcCklIJ4V3AOFCUFlXcFz99EfHDQEq-Od47c-vkv3U-Oku4a8hhs3AwbTun-433kHmrKhVCf93FPmS9LDkN-2x8QOGySeg3SLEHxgbnZngl9CIYjs_jhfh7gfUPtpHWHkziRWmKW3h16BOUj79c8nsXSj6kKJlJbKs4qrNFGdcivcc4tFsbKjFu5Sl3H0wNF3AlS8EtVSQabfXocMkgxPJv4A5olhXdRSy2Cj11hJBpqKLAuQPKgZhvclkeiXzGISlQjDGuEm2TFhZIjPQWw0v3Z_C9onSfLtDIWOOUxbNDkeZeW3z045ptuwgJ-iz_tcRgYlrj5GeYB3vKhPdzsMfg081N0WX9gWAzdsO89CNi_7KHmYQXdnTDF1tQ2gdUCpIHU8JXuYb9mvGj8htmVkncQVIMtZn91yy2ui-xytjfTTSjktpTO7NF1PGehT1zS6zZd0p2tBSYPLI2akVGFuc3_Yy69zt-6-xvkSOmKYHy0A2cafbfQfxFIaP3EuIMXwRT2PcIPwdRHGYISbgpMEKMLlv_oyGxjs0-j71fAI44Qwd_-NI_5QV6hCr9DLpf4MGsw3_AOdnUTmBgDh8_-S4Ud1XAwIqY8uybaCOiKeE2ZKwgsJTtNQoW16ckx6NP5gIlg_10aullMBnd1-jAiGXPBTlu4VIFuvyzAKUwMI9m3YBLC1-p2kX1qXxqxAwfL6mLmyEMJLkcvgYLAeZKb4yxj8COdpGA_Zmwf59-9zdJVg9TooRVaX565TN7M2WMTDO8vPcuOxziVl_md2UuZ3JhH47RlTrYSMAR_qUSZVJ7Fswq3kzYMmA80HPMoLjqWcgyhpCmJzbMwx_yIzENt5FSlzigPk57hX_W1RuBzll1aVZy27Yet3lotby7DBK_lkGr8HoS5JiTPm0blN9A4Q7T0Ay-Y0niDQmz1n4PJohwgg5VKchgOyfx6hfv2kWgPrVaOaT446HCxPdd99EaZnoLl4stbkCeJVhe4zANj6mZMgWAwNXG_a-33ICnfVkmQUYmkimsvxtKZEHpxf24RqvqC_yRILA2gDUjybvTDW3f6aQlfdT6R_xEB2GK7wJtVloo3SRyWzGyfdDhm8ha2iy0up9Pg-8YaCSSyAgJwUz18UYQ9cQ-LN9c3aXFYbRVafE3Isf7w89RzBPLqDwuQvXHMODPQ3yduD2vdbYe4xWE-uUngaSFaPegFGW52G01SHIHvmV0jP_P4-LolT5Cf3SBpruHdV8PJKW7rLthYSh-32XUZEo94SrzJsaW2nRecm1NjGvGKAdWohQ0DcpAaqZYtI79E6y6Sj_nsL7_xe2-_chHBsx-Fb8Uvo3BTtbsSruj3okjiHvNPSoVSiF92uG5iWgUseUuxsvnrW0uuL-pGD_qWFlEumpr7FGAMGRoRDjYJwLnJZBo8xkch1jM6ztrcuXUPYMXcHF6eKNKEMa4ShGrnbowM0xVwKpxwSEgaHy1pKq0_MwoRDEvlvB3jICp7TxvjetTWzX7mFazX5Ji4jTQOdc4P9kl_2vnkBVwWShI_xlJiL-AMh5AJgm_2P45wEawy6V3AvXoGNpNfyoYxB-EcdUrekWDFJbwdF04V_VjML4k0sKhKR1QMsOkJg9C3FqjNBfLq7jQ3ANanQQCi9Zes1wp0_ymily8KRGDnSp2LgXX1LXGBQvUSk--g2ifXeIZfRXoFK20ID-A2CU6WuWcNi_kDR4HH5Iyxw2pSxi2TVelVKm9WNG1fbhoxbWJkhgtyhYdbVv_ry3P3h8yuk7Y-dDGEO_V9mAh9ape-qirMT0XoopCSTiXnoj1j_nim_qQCw7w5KEhcDtNXdbOUyzK_poWlSCcN-gDR4BCAvBRTXHGAU6dM9eqyR7cvBszyeBDAo2l3go3jBnBNHLEoksqLilYU5GPxUuobim0Xyw4LaEYWeCalTMSPAAX_qvHDwGu95wchIb_5khF_CtZ6wKEqiMD1gOFeWqNUJwl11AOil69NqUMxRvrh3lSJ9wYFWNX1h9OpeTESgsrTAovg99oGyzEGOlUs4K9lY8x4f_UAFWOwZwtO2bSDe7R9vFEwEEgQ__YRJGf-mzcREWk1I6in-arWipi7wNsuC54B41lr6W_fnDm8vPh3hNCWHVOocaIvNuztSY53ZR6W0agk4pNub7kl8xZPi5Dtj0F3tqVqZC4VU0vfK9MUqjYWyfo_lBfx2A"
      },
      {
        "data": {
          "filter": "||mercadoclics.com^$third-party",
          "listName": "easyprivacy.txt",
          "query": {
            "d": "ScRhZru-oasdKhunsVVKEQR5lKnwOJHspDHbSFeYnq9A9t_tsYSbV6Goik0cBPxNnfy40g2cTzwLhcXb9CIKdJmY_h5tBn9m-SDX0V24m1z40avaDOBeiXCM3vDE-RUkLBR3tQsoVOxuWmLdsKQrgPomfuL-IzNwj3IiR_oL3RY_4RwmbiDwUmQ70Enjh2avGTd7yBnmLfO7i4cdz7UlxQsAr2xRPfXugQzen_34F4L3bh9OP5H8WooWtOHB6dncHASjTtbC7LQtRL3PeefPurpPOp1pA6zMCm1czdS7XeTQcMQcRLs2EAAmNUXrjijOd3Q6ErAH9gGgl9xiiBS4eNnOTUBTpHxSKynTpQTMpxdqXdANyghewVe1jyq6VEzGVK6RL0i2LiBRO_uqJcxMjCF5BrHfKlzQOXe4jpvCo5d9we28sIlgk5USJt93TI8Gmn4mH1-YIUlSnFW3FQ0dKRebpDtVb2V2ax4F4zxnWzS-sK-BH6ObOQqXmaYvJ0NK0UhkaLMaBOyNPTK1ACDyPx2Sl68qvuUHZYBRTWAK6cClmFI3qrgDZqfs7XxNsyQnMa2emihJzeSpQPf1iHolU5VENgOjLtonznuRridpWZnNt3fS5n6NA607ieEDUT1iX9aM2JCHRs6addG6USrTfEWBQCsoU5h7_9H5APPLEKCa4COZPSiclwwo25_vNVCnRz032zoJHWm94tpoJgIOj8LkDyLjgweVqrBHqzG1x1G4e5ly8PFxXiy7xQzHAiWg9ws2UdTA3o4HST51fo2PVt2WA-tkjG3mroeFpNksMzib2m2swYh-6Six7O8tR6IDI_V47QTevpLH4Ldh0a_yF1kKiCBz9EgKqQfK6OkLQp7eIF7qtxq5-ChaRUAeB0A5Bx3WH3sWYQmTYxnaHc-vAyfRjdWsU1GE6JG0KzT1BtkLJkI_k2aWXELK6UpINUW5upXPbTwBGntGswmDSK9kfLy9XXri_s8BddvSKkvCcHajB8lhDYvB9Y1Gul3Wgpi9Vp2ex406-1eru2aR311WRemJ4IYwwb5q_UQBqPgz9xwvsMXcNLOW3ek7n61dm0EPtSqSeGOsxB0nuwqN-HLq1HVFJoE91vJz2g6B1HhG6fwCW4s2hs3dzKfJQNIRK680c4FV_TtdIsvE7r4YL_cV4RmzPZ0WaHlLFv7fx2iWzrIiScQUN-FNVof58smJvqLzUY-ZS3d03gds2T_6lBxvzbQ9jtWrqa480-hcu8g0sUJtYYmA-ge8LWTeIEpAex8xzzIswwboqE9PH9w5OJq3QqnKaHeEj_bYHksjjV1pMB2gRkOi5kEkN-tfj1m67HQpkZdp35WXuDdP0UOUHSWvP-qYWtvqTLunE5aqECaPfiehTl-QCS_HEWH_r5XnTero9gSmnvzWtMi16k-AuchuO_dhbr9uBtX7u87Lpngfc5Biv0AdcUnO7XggjP4sW9A0c5Rh_bFfeltpPbhc-bnOa8JnF_tq4D1KqFbuOLyoyjorJlSf5FzRFbZ7lmX6dSaKsHfHlPP2XbVWArmu5fOO8uQksoOjNfEjJ6K2xdctV-oAFJ4oINoqDLiq92coIcKYCxcJ06QRLF7U3jzDJpPFeKjka8rp6RrefPS8vXBs61kR18B0RupUzMrtSTx2cpgKPnBjKMjBtv-ggITVPbmrvHPXYOAisATfsCesIl9fyRjD291udh4jfYeze1_716Iv9yqWcGMNB0VOnSJc9uNnRz9Xhpc-E__HiEV3js-_m8IQYwz_Pu1bjX1wUA9rTXrYaob0tDlHLf3tKnFbb9ELjrCt3Aff4O0MX3XaYgRq2LC5Zz0Wr2JsbbNwjiHOhG0x-i_5u6L6ZyaxF6cH9UMfjLKxaKuSWFcVt6dIEMur3cUU-IkCkNAZljZnk_K5iq5qCNFYFORE1mMbRMsjWbbZd2EUkseMMgDVVrbD9q3ITTpRFRJF0C0YkT3MfalB9Ty3DLmWqTZZQUv8_a0ahfgcC5QNJq8ujzQnl7yKkCMfJ6WnYA1_vCFeQJ5sLO8D_ivlMZuti-Os5UwEI-judyRg-IrT9JxBSnV_usia8JB8UAPftnqCRybb9_3fKJKOUO3PpnnrxPiVGdZYXIz6W0CFX3EkjU0Lv9TXk8EyTS5KJZoMADngBNh9OrDEFIXt3PTwgTQ-ZDXVTgd6dGJH6zE64kHX4TSlOE-Eanocns77G28uTUwLxribknUuZomAgDDqgnyQTTnXXfiFJDMucbBjZo2BKtqUWH_-PJgHVNmYRvKp-gk881w_c_PXZP5SUQk_SaUAzr7AYU2A2AgLIakw_dPVwepfRsYxCdG2tocU3N6NmAsUCylyv7gTauErQKTyRO0TMlWmBFDBH9lDgC0NvxufEuDPj1lTNwHNsfkzZiH8a2KMHEdL7SX70bO7FELnK1SDehHaxJOb5I5goSByrp-nwgPLw23G7zMYf1KOZC3CglI8UrjvcAQIU9R5rizeyZrfe8Zfc3Saor5bWp6NyszM3_I5zXzz4oo6GW3fOle6pywGGzr5xhwxFJJ3Fl8mQBsou3f9SwmBO8ZIMbqURCtJsDUo-HJC_5q_BN9QxCo7F4o_uyQ56t6_Mi3JTYg_MYlMk4Vje08tjZe_Wvwy-jRKhJHHOrSKMSvw4WwgOtqK8Eo_aQrQmjmpLA0Z-Iw2dZPemQkIA4E5HYBs1IqoZqWinXYbgpboli3XRw6Te-mQ40bq9OlxlT2J_TpzrJWbjDDPKn9l1E2PB6kjuVO0RV3HK3yum3FF3ouuF92BW4fV"
          }
        },
        "stack": [
          {
            "fileName": "https://www.mercadolibre.com.ar/",
            "source": "ThirdPartyTracker RequestHandler"
          }
        ],
        "type": "TrackingRequest",
        "url": "https://print1.mercadoclics.com/display/prints/MLA/count?d=ScRhZru-oasdKhunsVVKEQR5lKnwOJHspDHbSFeYnq9A9t_tsYSbV6Goik0cBPxNnfy40g2cTzwLhcXb9CIKdJmY_h5tBn9m-SDX0V24m1z40avaDOBeiXCM3vDE-RUkLBR3tQsoVOxuWmLdsKQrgPomfuL-IzNwj3IiR_oL3RY_4RwmbiDwUmQ70Enjh2avGTd7yBnmLfO7i4cdz7UlxQsAr2xRPfXugQzen_34F4L3bh9OP5H8WooWtOHB6dncHASjTtbC7LQtRL3PeefPurpPOp1pA6zMCm1czdS7XeTQcMQcRLs2EAAmNUXrjijOd3Q6ErAH9gGgl9xiiBS4eNnOTUBTpHxSKynTpQTMpxdqXdANyghewVe1jyq6VEzGVK6RL0i2LiBRO_uqJcxMjCF5BrHfKlzQOXe4jpvCo5d9we28sIlgk5USJt93TI8Gmn4mH1-YIUlSnFW3FQ0dKRebpDtVb2V2ax4F4zxnWzS-sK-BH6ObOQqXmaYvJ0NK0UhkaLMaBOyNPTK1ACDyPx2Sl68qvuUHZYBRTWAK6cClmFI3qrgDZqfs7XxNsyQnMa2emihJzeSpQPf1iHolU5VENgOjLtonznuRridpWZnNt3fS5n6NA607ieEDUT1iX9aM2JCHRs6addG6USrTfEWBQCsoU5h7_9H5APPLEKCa4COZPSiclwwo25_vNVCnRz032zoJHWm94tpoJgIOj8LkDyLjgweVqrBHqzG1x1G4e5ly8PFxXiy7xQzHAiWg9ws2UdTA3o4HST51fo2PVt2WA-tkjG3mroeFpNksMzib2m2swYh-6Six7O8tR6IDI_V47QTevpLH4Ldh0a_yF1kKiCBz9EgKqQfK6OkLQp7eIF7qtxq5-ChaRUAeB0A5Bx3WH3sWYQmTYxnaHc-vAyfRjdWsU1GE6JG0KzT1BtkLJkI_k2aWXELK6UpINUW5upXPbTwBGntGswmDSK9kfLy9XXri_s8BddvSKkvCcHajB8lhDYvB9Y1Gul3Wgpi9Vp2ex406-1eru2aR311WRemJ4IYwwb5q_UQBqPgz9xwvsMXcNLOW3ek7n61dm0EPtSqSeGOsxB0nuwqN-HLq1HVFJoE91vJz2g6B1HhG6fwCW4s2hs3dzKfJQNIRK680c4FV_TtdIsvE7r4YL_cV4RmzPZ0WaHlLFv7fx2iWzrIiScQUN-FNVof58smJvqLzUY-ZS3d03gds2T_6lBxvzbQ9jtWrqa480-hcu8g0sUJtYYmA-ge8LWTeIEpAex8xzzIswwboqE9PH9w5OJq3QqnKaHeEj_bYHksjjV1pMB2gRkOi5kEkN-tfj1m67HQpkZdp35WXuDdP0UOUHSWvP-qYWtvqTLunE5aqECaPfiehTl-QCS_HEWH_r5XnTero9gSmnvzWtMi16k-AuchuO_dhbr9uBtX7u87Lpngfc5Biv0AdcUnO7XggjP4sW9A0c5Rh_bFfeltpPbhc-bnOa8JnF_tq4D1KqFbuOLyoyjorJlSf5FzRFbZ7lmX6dSaKsHfHlPP2XbVWArmu5fOO8uQksoOjNfEjJ6K2xdctV-oAFJ4oINoqDLiq92coIcKYCxcJ06QRLF7U3jzDJpPFeKjka8rp6RrefPS8vXBs61kR18B0RupUzMrtSTx2cpgKPnBjKMjBtv-ggITVPbmrvHPXYOAisATfsCesIl9fyRjD291udh4jfYeze1_716Iv9yqWcGMNB0VOnSJc9uNnRz9Xhpc-E__HiEV3js-_m8IQYwz_Pu1bjX1wUA9rTXrYaob0tDlHLf3tKnFbb9ELjrCt3Aff4O0MX3XaYgRq2LC5Zz0Wr2JsbbNwjiHOhG0x-i_5u6L6ZyaxF6cH9UMfjLKxaKuSWFcVt6dIEMur3cUU-IkCkNAZljZnk_K5iq5qCNFYFORE1mMbRMsjWbbZd2EUkseMMgDVVrbD9q3ITTpRFRJF0C0YkT3MfalB9Ty3DLmWqTZZQUv8_a0ahfgcC5QNJq8ujzQnl7yKkCMfJ6WnYA1_vCFeQJ5sLO8D_ivlMZuti-Os5UwEI-judyRg-IrT9JxBSnV_usia8JB8UAPftnqCRybb9_3fKJKOUO3PpnnrxPiVGdZYXIz6W0CFX3EkjU0Lv9TXk8EyTS5KJZoMADngBNh9OrDEFIXt3PTwgTQ-ZDXVTgd6dGJH6zE64kHX4TSlOE-Eanocns77G28uTUwLxribknUuZomAgDDqgnyQTTnXXfiFJDMucbBjZo2BKtqUWH_-PJgHVNmYRvKp-gk881w_c_PXZP5SUQk_SaUAzr7AYU2A2AgLIakw_dPVwepfRsYxCdG2tocU3N6NmAsUCylyv7gTauErQKTyRO0TMlWmBFDBH9lDgC0NvxufEuDPj1lTNwHNsfkzZiH8a2KMHEdL7SX70bO7FELnK1SDehHaxJOb5I5goSByrp-nwgPLw23G7zMYf1KOZC3CglI8UrjvcAQIU9R5rizeyZrfe8Zfc3Saor5bWp6NyszM3_I5zXzz4oo6GW3fOle6pywGGzr5xhwxFJJ3Fl8mQBsou3f9SwmBO8ZIMbqURCtJsDUo-HJC_5q_BN9QxCo7F4o_uyQ56t6_Mi3JTYg_MYlMk4Vje08tjZe_Wvwy-jRKhJHHOrSKMSvw4WwgOtqK8Eo_aQrQmjmpLA0Z-Iw2dZPemQkIA4E5HYBs1IqoZqWinXYbgpboli3XRw6Te-mQ40bq9OlxlT2J_TpzrJWbjDDPKn9l1E2PB6kjuVO0RV3HK3yum3FF3ouuF92BW4fV"
      },
      {
        "data": {
          "filter": "||mercadoclics.com^$third-party",
          "listName": "easyprivacy.txt",
          "query": {
            "d": "DB2gxCcHy46hF4O1SGx9F0XgL-zsZUuTQUJ_zgIvu5_HgMNIvPzDRaIdIFMiAUopeLWAP5EGPWc0KDy05X4xoWgcJnOYwvKg-8Ou8NwzElyK6S2pxTKJhjlULD91pmIr6ASyYj6jUdGQTgco8Gf9veBfPEjYvJ4xluVE-VLVYlAUDPSsBL4Tv0XIcGLOGijuWzYYBlEOnpz4_YrC4Qo06Yi1rKbhyptSLkEJEHQLcz4RmLCYTdPyAWeYxOs3RZw3uYLHVaVVi_rt9TxxarkE1_yp4v5hZNUfO4rfAWge0-WTEhFJuiD6bR5QEdCmiO5L4AnPULzQmWzmIvRSmdojfCR97HsVOUHAHKleZyFwhjshA7GAHkMAJSBIMhrrbV7zRMtCdN4qKdAAk8tYb8VWhhs5_XaKdcvu7RJ3-ImNrN9AwNev69_LjxEjRXwH75_2EKl76zHm_m9cgQ_17L3iJni91KQy3RQ100Pdnv_gpLdvPR0QeVpdLwa5NfZR6sLVMyMBFsof2IGu7yNrTNWjs49HWIZdCF1FKAZW2O1Yt1vv8WHKSgXt1qbpR9MYAPnzZRGghe0JOuhPiObsGmhBGe3vRRZzRl32NztQqioaP2Zus6vxVcOifetoTzhsHpkh74t0uh9yLR0NYoXuUheb1aQN-Z_-FCGMb_SnxFx6bqCnne-EbMaPMZRFlcS5390hTAcRjz7xIIKRil8xZgCb1EVVENRgkfoPONfQXywZfkVyv7hBlaYO_FGMxPksgn7B6ZTDDDLBe0vxZ8w2bgWufvjtQ5ZFsvhXr5do3iEipQaguX-OaFYAmo9gzdw6NieuflUmUjtOFXol-1IX-L08l7WFUFozUXTIy9LOVLsESTARW76ASa_1MBrcoWwObTv3qGTljJnNeptIf-OCqcl90pRGkB1RRMdH_aDkh-3V9iNBj9TUBmK8-2CbVT_2_Ju2NSoG9QBw33upSsLbHfjvcCxxobKdDIaiiLsWtJlye5pEnv5XPFWLJs11HUBeZzBRbC9R4Jz1LRehVZaOpjioebwtZzrD2JmxPe-_jgqf-sCpclnoh1SRFe_nocJXpMPCaEU0L_fN-hEuGPhb4FRP-L-VxiBTvXVo7w0PplSqtAwIf9fRIllOmE7lBRWw0aS7ImoxLI5sMZhjWtgDBTcElV0TApkF_9Nt_0lXyNj8XuHQR0SpvW0ps0qURNXLdY7PQhoT_2XlDdekcSun1lbnH1txO1T0r3YYzzGSuAxQaTQ13epO3Z6Xbh0vaqITSrKshsXLuFNNW-JqLCXsdELDQMkaJBxjMKCmrQXNzaaeLc482CjDaZhHuwH8Wwb3Jo39agOwC5rERIfq3glv5RocHyCpZnzfOnKiEMrxC7zlbLA4OhWsHJKz7tCIXNPSuwjTm5sp7cgxS7bOnkCOtgDtTiDAox8QeBOfdDIXGA-Dea_gqDCm6vjGjT2lT3L64eP3-tRPwueo7g05r-h0kCzWCmGlIfKzQPt8biXhHoFzt-LG47IulAE_FQ1hr0V-r5Yfm6Gi9vqMaWbF6FjWmUOneRLMjZNwO64yNd9EUq7uip4LeSEsGbLNqkK5r2KwIuaZz01U0KTEatWiQ1zJ6rxqBoDeXIFDhNaw0AKJd7i9OMFgVF24gnScHPu_vzD3Z4D2ortE56_LQK_HfcqY_80QX9wIDgGc40zjF63V9U6cSHCFkU7CAWxif5H3jhEAFTZRriOG8TqecpGcqGv9anCa8iX4GOeS-9vp-xh8EUpr0Zz27aiiISIUEd0voD_j43TRMmnnN18Z7eyDmIazhoyv-qO8-ijFfoFGNcxTPNdBdVLhMLhQqxnnCikGmMHhflnd_FTV1EwvbFhNBaTuuGTnq9NloBMyeRj-WSfLwVw4LvQZ9E_psAZa_2hTgckdnKQT-pHYtcHqXRUvI4_1BVD6g2xk9I3eW6ZuIigVwSwa7wsZRWAuzIxfg-b4LeNywwCz4ywptBcu9LM0r-BkiQc0wguaN-zReX8QkQ9p-uX_2szjmlKEU9__hhZ_U1stZhzDRruyTYeL8lajc2xbGisgcrLhDldb76Q0dKziKeZ4BUwdTbCOXj68LFvKzSsj12F50N6dX2hl6dX3sXDYBuR8iAuvBmYWbOJ7jE98evl9mYPoKdi0eZMN3cs9ZiN_15qsyajUSe2SOOVmiyfqo9nHc1aRzuDLYyRzXWFby8nkOf1zIELOP5007oUjhJ7SpcsCYx4nxjhk8zOJSHIb9U4rYEFYoVZnj_zQtpReo3_VGOGzP9g4jHdXD0KdcGRkCGOBXc3hIrBC8dQXoYdx4VStg_6YLkgL9MjS6lBvpztLRV5vYQJc6aZA7lADcN6nQeqcweGM3CTh3sSHnqOmEV7H9rCX8FE5qsXI5w3tn31eDCQiVIsYIOX9MDEQ7-sDTNxzo6k0YWkCPt1syFFZHIuPDl58AIxVZf8lUzx2Fe4bizfrF1B4DSg8lLcJEtocUZjVtSBgZOHNVKGVYkNtxt7_L9Wf47hmQVQQidccVM97mZE7pE_do2gH2AU_dylmNrIIXa8c0tlE0dow3ip_MhS9oNKozCPnqf6wsudX5s-KFTi7pOhxo6wz5_8gZxjoo7wOpu-_-TvNRXu5YeHyWp_yL2nJ4kp2njOlLpD1BP48KhcUn2V4VhtoBq2pdIowKrnlEgS2WpxYu8YyloKvf_70qVjzWeafdIbFK40O0tnDpgstIKa6E-Cy-LQevJe0vnacdQlfDjQjaN_wdEXOi8kKZriAytNwrUOpANLT5PKLkA"
          }
        },
        "stack": [
          {
            "fileName": "https://www.mercadolibre.com.ar/",
            "source": "ThirdPartyTracker RequestHandler"
          }
        ],
        "type": "TrackingRequest",
        "url": "https://print1.mercadoclics.com/display/prints/MLA/count?d=DB2gxCcHy46hF4O1SGx9F0XgL-zsZUuTQUJ_zgIvu5_HgMNIvPzDRaIdIFMiAUopeLWAP5EGPWc0KDy05X4xoWgcJnOYwvKg-8Ou8NwzElyK6S2pxTKJhjlULD91pmIr6ASyYj6jUdGQTgco8Gf9veBfPEjYvJ4xluVE-VLVYlAUDPSsBL4Tv0XIcGLOGijuWzYYBlEOnpz4_YrC4Qo06Yi1rKbhyptSLkEJEHQLcz4RmLCYTdPyAWeYxOs3RZw3uYLHVaVVi_rt9TxxarkE1_yp4v5hZNUfO4rfAWge0-WTEhFJuiD6bR5QEdCmiO5L4AnPULzQmWzmIvRSmdojfCR97HsVOUHAHKleZyFwhjshA7GAHkMAJSBIMhrrbV7zRMtCdN4qKdAAk8tYb8VWhhs5_XaKdcvu7RJ3-ImNrN9AwNev69_LjxEjRXwH75_2EKl76zHm_m9cgQ_17L3iJni91KQy3RQ100Pdnv_gpLdvPR0QeVpdLwa5NfZR6sLVMyMBFsof2IGu7yNrTNWjs49HWIZdCF1FKAZW2O1Yt1vv8WHKSgXt1qbpR9MYAPnzZRGghe0JOuhPiObsGmhBGe3vRRZzRl32NztQqioaP2Zus6vxVcOifetoTzhsHpkh74t0uh9yLR0NYoXuUheb1aQN-Z_-FCGMb_SnxFx6bqCnne-EbMaPMZRFlcS5390hTAcRjz7xIIKRil8xZgCb1EVVENRgkfoPONfQXywZfkVyv7hBlaYO_FGMxPksgn7B6ZTDDDLBe0vxZ8w2bgWufvjtQ5ZFsvhXr5do3iEipQaguX-OaFYAmo9gzdw6NieuflUmUjtOFXol-1IX-L08l7WFUFozUXTIy9LOVLsESTARW76ASa_1MBrcoWwObTv3qGTljJnNeptIf-OCqcl90pRGkB1RRMdH_aDkh-3V9iNBj9TUBmK8-2CbVT_2_Ju2NSoG9QBw33upSsLbHfjvcCxxobKdDIaiiLsWtJlye5pEnv5XPFWLJs11HUBeZzBRbC9R4Jz1LRehVZaOpjioebwtZzrD2JmxPe-_jgqf-sCpclnoh1SRFe_nocJXpMPCaEU0L_fN-hEuGPhb4FRP-L-VxiBTvXVo7w0PplSqtAwIf9fRIllOmE7lBRWw0aS7ImoxLI5sMZhjWtgDBTcElV0TApkF_9Nt_0lXyNj8XuHQR0SpvW0ps0qURNXLdY7PQhoT_2XlDdekcSun1lbnH1txO1T0r3YYzzGSuAxQaTQ13epO3Z6Xbh0vaqITSrKshsXLuFNNW-JqLCXsdELDQMkaJBxjMKCmrQXNzaaeLc482CjDaZhHuwH8Wwb3Jo39agOwC5rERIfq3glv5RocHyCpZnzfOnKiEMrxC7zlbLA4OhWsHJKz7tCIXNPSuwjTm5sp7cgxS7bOnkCOtgDtTiDAox8QeBOfdDIXGA-Dea_gqDCm6vjGjT2lT3L64eP3-tRPwueo7g05r-h0kCzWCmGlIfKzQPt8biXhHoFzt-LG47IulAE_FQ1hr0V-r5Yfm6Gi9vqMaWbF6FjWmUOneRLMjZNwO64yNd9EUq7uip4LeSEsGbLNqkK5r2KwIuaZz01U0KTEatWiQ1zJ6rxqBoDeXIFDhNaw0AKJd7i9OMFgVF24gnScHPu_vzD3Z4D2ortE56_LQK_HfcqY_80QX9wIDgGc40zjF63V9U6cSHCFkU7CAWxif5H3jhEAFTZRriOG8TqecpGcqGv9anCa8iX4GOeS-9vp-xh8EUpr0Zz27aiiISIUEd0voD_j43TRMmnnN18Z7eyDmIazhoyv-qO8-ijFfoFGNcxTPNdBdVLhMLhQqxnnCikGmMHhflnd_FTV1EwvbFhNBaTuuGTnq9NloBMyeRj-WSfLwVw4LvQZ9E_psAZa_2hTgckdnKQT-pHYtcHqXRUvI4_1BVD6g2xk9I3eW6ZuIigVwSwa7wsZRWAuzIxfg-b4LeNywwCz4ywptBcu9LM0r-BkiQc0wguaN-zReX8QkQ9p-uX_2szjmlKEU9__hhZ_U1stZhzDRruyTYeL8lajc2xbGisgcrLhDldb76Q0dKziKeZ4BUwdTbCOXj68LFvKzSsj12F50N6dX2hl6dX3sXDYBuR8iAuvBmYWbOJ7jE98evl9mYPoKdi0eZMN3cs9ZiN_15qsyajUSe2SOOVmiyfqo9nHc1aRzuDLYyRzXWFby8nkOf1zIELOP5007oUjhJ7SpcsCYx4nxjhk8zOJSHIb9U4rYEFYoVZnj_zQtpReo3_VGOGzP9g4jHdXD0KdcGRkCGOBXc3hIrBC8dQXoYdx4VStg_6YLkgL9MjS6lBvpztLRV5vYQJc6aZA7lADcN6nQeqcweGM3CTh3sSHnqOmEV7H9rCX8FE5qsXI5w3tn31eDCQiVIsYIOX9MDEQ7-sDTNxzo6k0YWkCPt1syFFZHIuPDl58AIxVZf8lUzx2Fe4bizfrF1B4DSg8lLcJEtocUZjVtSBgZOHNVKGVYkNtxt7_L9Wf47hmQVQQidccVM97mZE7pE_do2gH2AU_dylmNrIIXa8c0tlE0dow3ip_MhS9oNKozCPnqf6wsudX5s-KFTi7pOhxo6wz5_8gZxjoo7wOpu-_-TvNRXu5YeHyWp_yL2nJ4kp2njOlLpD1BP48KhcUn2V4VhtoBq2pdIowKrnlEgS2WpxYu8YyloKvf_70qVjzWeafdIbFK40O0tnDpgstIKa6E-Cy-LQevJe0vnacdQlfDjQjaN_wdEXOi8kKZriAytNwrUOpANLT5PKLkA"
      },
      {
        "data": {
          "filter": "||mercadoclics.com^$third-party",
          "listName": "easyprivacy.txt",
          "query": {
            "d": "aIXHuX-FmqCa9gki2EDg5I4Jb4SZsSWHqdAzus21bryZ2ZntOC9soey-Ju8vxrQwM4KQ0AR_tLofv5TfHA75SqkHbqRANPWk8ohq5rDZBMrQJTruEx4mUZnJk7H5T6aa7EIqhRsC3JyBtAKb9wR3yDWNL_ErcUo4wHfCG-TK6r_0x5qfeaFqMN-bDM4EJuUF90FdYNcSWIVj4nrpVBuH-sqZ8YM9byMtRXh4FvOzHevfduAjrQq3cIb88RWD1Mtn-si2TuNWIMLAxTTHbs_x-bcPf_UXHklSwa34fv2NvIiMe9xEWspRHvW3FNfEv58p0LENYTKgQwFIX1U1l7LVwEN47WGbox9zzYLj7iyICbcdlxO4N0lOu4RNW16yvMOfVXTzIJdSsPksnKRPuQe2kDh1PqVrrJQaK7TJd3-5cbIJg_qhvDNIeUiDvz5X8yCTIt1Y7UZgD2ln-k-ycyJkvRRKUT5PoUVvTmq0kM1WBJiRpWt8XfrF6mux5RFXWwg-pnfhK3NxGodTIG89sQDNLKotOrE6qSCzbfpiHciEwOj0obfYkQyHO0lZNH-XubWkxI0jVt6d7PXE2oZz-NnEFqMu2I1wymwmpiIJa5LihKPSWojnDUSiXduudlP31ZZt-put8ZC-DMxooxovjLxAfiryXQlrJLCcB9MvuTdBscrWkznDFJvkiFZszycRhgY53PRUgUQ2jCejt18gnd4j6FPheACAqxeDOrfJIDrMimVepwATftJoMYAD3ItI9tzcMKmBCCTBktE-IMhe8v5VXQgmIXcrkU0k0pX1YKXxr4r0SCAKRIY0F1X-elz6BYUoSve3l94-tbCCfZGvi77CWcEkh3SIfvAvMFv2WSsiER3DpCrBbO5WxFTLLHbCgvW9vSXh6TxXgW-NlEyGfUD9zPg8wCa4S09TBmin6pyigPahmTbmdhPuY3siElvpMiXlt3jfcNfmoL_FRDmmG3yblQOkz4bW4sYfSFTbREk33TS5JbF39kobWIeQv4Y2qXIx3yldhUWaunOXXgx6poEDVX6kH-6nLURvM40ap77W5y_na_9DZKvxtabSHxMvxVyQc9cayYDkPdS1PuagWQWaRkHdqhe8ndAWYbcYKlXagqYBV3PeBm9TN2H53cYrL3_VA0NLxHnd7ULXWlEI_LQYyOf2KKS8s3exbUGOMfPjCs0RX-ch31cOMAQtmxydjKF9fvdw3PFFJBJJJWDlpuAdXXLyXFNgLziEW2myklW7X4_rEwuIYQdKduEsGosqJDbYJuDwi2GkgFULS6pdJroQb4R4hNGgXT0K2_YIY5i0FBfFeF0nPvEd2YFw56MRt1m9Pw7STXxHvcm1LOb4UJ3N-zQYOWiE0ganecIHazVgsIuAvZ5tuXjieDa8v_bXvb5QXY6SizLbSyE8PPcfknmN7TPdvGBH2q4UnT8M35h6lH_iEGREcakUOnoLqagcybObCbQ3FwXlTGHSEyLBMq_7iqzWBgFw9DNqUVcr3xR0PdlHo0AUSTIRAF2HMec3SjqSrVTqyAjpConehC9T6e-rCX0EGxAbgosvoWWml7ZNn2crQlr7P9bmRfpTbInOpqOiNDzFAokRt4GbHdAGwVPt8oZ86jB7HmRzoxtIKvZlI6rnvNUYrBB2uWfmrYsjKeEUaZdeBU2BRwRJeeFYRcSxu4fa_xhxaFFx1-o4-PmR46uPZSN0v7PDPlNfNulVoQ-1UdFHAEF0Wl8ctNEOY-NH9YiY29obfEhCFWIZrOJD19SnIPCBK0RiSYEEKdmUVUiWDEllHAWTW4NYZbI6QApRZySY8UwfCJq7K9aRZoU2mgOTtlRTFPnmlzLEPBBwI94_SweulKnc00LhEqhxa3Uk0_ZtbTyxQ5iyktKTXlqI_yzWoBeij1Q8tAvZCUkFGHTkwxDc2-EoB04xZd0nxHrH2w3TRmZWbj3tfFAaT62XCRI2Q5I-4RcsFKL8Q2UTloTCcOzF_gUTIh_bX0MndDvF9lq6hmd9pGrV7KRXpLK1g782ceOygy4t3jg__LMzRLCPlQKcnTEvDxAaHwtdBgvX4ekUKNLGbsDbFCJVD0t67ofHyo4vCdLMdw_Y_08WRSLvJyNSoDIZWZk74Bi5jee43Y2B0rQAbs24xDsj-uW-p5a9yZvtwbpKbmbyWq7XgTCLPaxpcHkFbrT7qozW4XyVdDeuIDPgazbKw1r5DbJzm7YR4pQem2n9tM2QIJN4RR8Kyr6rmCfCCH6F3bISjKYYrLzu4fz7IBl38yoGGYpLsD0aWmO8AovpX4zfzkrdm65HBLyImykKAPrj4hE8LBPm6Jo_2ShKA4Y5uGq5HAVxkX6CJJ2MVGCxNlVkMFlJXFP5IyocYiWN8C75eT9L-RJcGMM_l8lW207l12RwL48ucOL16wiPFNsPw5R5KXa6IRd0YaNWr8sUBTeOTifpoCKv3gqVHPvw_k8r6OM_5gIZg4hMdAggQm8XmKtYJacwAN8yfoVeElRSkWSDX8r4ULsLl-vuAQrG4mkwF-5ao-aDWghkR457t7cyzxVgsF0F6VxWPtUUILOIkQKG98tLjBSPZPzFvolKWtVAX-fIPJ642_NmhBEKnadPw3dzTkjEfsIWoaVfAn0qiGYbMlodEl8yPQy39st-rsZ6DFl--sgKgfTfdrhYId7HA1NbOYJrlgy3t454_GAVaLWiP6Z1PHJKktvB3EJ48_cFPXgaFcidUoA_fRqhHUZ9il388YZtKTE290e8yKDg9KuSYPVm8p6sHUep7iPl"
          }
        },
        "stack": [
          {
            "fileName": "https://www.mercadolibre.com.ar/",
            "source": "ThirdPartyTracker RequestHandler"
          }
        ],
        "type": "TrackingRequest",
        "url": "https://print1.mercadoclics.com/display/prints/MLA/count?d=aIXHuX-FmqCa9gki2EDg5I4Jb4SZsSWHqdAzus21bryZ2ZntOC9soey-Ju8vxrQwM4KQ0AR_tLofv5TfHA75SqkHbqRANPWk8ohq5rDZBMrQJTruEx4mUZnJk7H5T6aa7EIqhRsC3JyBtAKb9wR3yDWNL_ErcUo4wHfCG-TK6r_0x5qfeaFqMN-bDM4EJuUF90FdYNcSWIVj4nrpVBuH-sqZ8YM9byMtRXh4FvOzHevfduAjrQq3cIb88RWD1Mtn-si2TuNWIMLAxTTHbs_x-bcPf_UXHklSwa34fv2NvIiMe9xEWspRHvW3FNfEv58p0LENYTKgQwFIX1U1l7LVwEN47WGbox9zzYLj7iyICbcdlxO4N0lOu4RNW16yvMOfVXTzIJdSsPksnKRPuQe2kDh1PqVrrJQaK7TJd3-5cbIJg_qhvDNIeUiDvz5X8yCTIt1Y7UZgD2ln-k-ycyJkvRRKUT5PoUVvTmq0kM1WBJiRpWt8XfrF6mux5RFXWwg-pnfhK3NxGodTIG89sQDNLKotOrE6qSCzbfpiHciEwOj0obfYkQyHO0lZNH-XubWkxI0jVt6d7PXE2oZz-NnEFqMu2I1wymwmpiIJa5LihKPSWojnDUSiXduudlP31ZZt-put8ZC-DMxooxovjLxAfiryXQlrJLCcB9MvuTdBscrWkznDFJvkiFZszycRhgY53PRUgUQ2jCejt18gnd4j6FPheACAqxeDOrfJIDrMimVepwATftJoMYAD3ItI9tzcMKmBCCTBktE-IMhe8v5VXQgmIXcrkU0k0pX1YKXxr4r0SCAKRIY0F1X-elz6BYUoSve3l94-tbCCfZGvi77CWcEkh3SIfvAvMFv2WSsiER3DpCrBbO5WxFTLLHbCgvW9vSXh6TxXgW-NlEyGfUD9zPg8wCa4S09TBmin6pyigPahmTbmdhPuY3siElvpMiXlt3jfcNfmoL_FRDmmG3yblQOkz4bW4sYfSFTbREk33TS5JbF39kobWIeQv4Y2qXIx3yldhUWaunOXXgx6poEDVX6kH-6nLURvM40ap77W5y_na_9DZKvxtabSHxMvxVyQc9cayYDkPdS1PuagWQWaRkHdqhe8ndAWYbcYKlXagqYBV3PeBm9TN2H53cYrL3_VA0NLxHnd7ULXWlEI_LQYyOf2KKS8s3exbUGOMfPjCs0RX-ch31cOMAQtmxydjKF9fvdw3PFFJBJJJWDlpuAdXXLyXFNgLziEW2myklW7X4_rEwuIYQdKduEsGosqJDbYJuDwi2GkgFULS6pdJroQb4R4hNGgXT0K2_YIY5i0FBfFeF0nPvEd2YFw56MRt1m9Pw7STXxHvcm1LOb4UJ3N-zQYOWiE0ganecIHazVgsIuAvZ5tuXjieDa8v_bXvb5QXY6SizLbSyE8PPcfknmN7TPdvGBH2q4UnT8M35h6lH_iEGREcakUOnoLqagcybObCbQ3FwXlTGHSEyLBMq_7iqzWBgFw9DNqUVcr3xR0PdlHo0AUSTIRAF2HMec3SjqSrVTqyAjpConehC9T6e-rCX0EGxAbgosvoWWml7ZNn2crQlr7P9bmRfpTbInOpqOiNDzFAokRt4GbHdAGwVPt8oZ86jB7HmRzoxtIKvZlI6rnvNUYrBB2uWfmrYsjKeEUaZdeBU2BRwRJeeFYRcSxu4fa_xhxaFFx1-o4-PmR46uPZSN0v7PDPlNfNulVoQ-1UdFHAEF0Wl8ctNEOY-NH9YiY29obfEhCFWIZrOJD19SnIPCBK0RiSYEEKdmUVUiWDEllHAWTW4NYZbI6QApRZySY8UwfCJq7K9aRZoU2mgOTtlRTFPnmlzLEPBBwI94_SweulKnc00LhEqhxa3Uk0_ZtbTyxQ5iyktKTXlqI_yzWoBeij1Q8tAvZCUkFGHTkwxDc2-EoB04xZd0nxHrH2w3TRmZWbj3tfFAaT62XCRI2Q5I-4RcsFKL8Q2UTloTCcOzF_gUTIh_bX0MndDvF9lq6hmd9pGrV7KRXpLK1g782ceOygy4t3jg__LMzRLCPlQKcnTEvDxAaHwtdBgvX4ekUKNLGbsDbFCJVD0t67ofHyo4vCdLMdw_Y_08WRSLvJyNSoDIZWZk74Bi5jee43Y2B0rQAbs24xDsj-uW-p5a9yZvtwbpKbmbyWq7XgTCLPaxpcHkFbrT7qozW4XyVdDeuIDPgazbKw1r5DbJzm7YR4pQem2n9tM2QIJN4RR8Kyr6rmCfCCH6F3bISjKYYrLzu4fz7IBl38yoGGYpLsD0aWmO8AovpX4zfzkrdm65HBLyImykKAPrj4hE8LBPm6Jo_2ShKA4Y5uGq5HAVxkX6CJJ2MVGCxNlVkMFlJXFP5IyocYiWN8C75eT9L-RJcGMM_l8lW207l12RwL48ucOL16wiPFNsPw5R5KXa6IRd0YaNWr8sUBTeOTifpoCKv3gqVHPvw_k8r6OM_5gIZg4hMdAggQm8XmKtYJacwAN8yfoVeElRSkWSDX8r4ULsLl-vuAQrG4mkwF-5ao-aDWghkR457t7cyzxVgsF0F6VxWPtUUILOIkQKG98tLjBSPZPzFvolKWtVAX-fIPJ642_NmhBEKnadPw3dzTkjEfsIWoaVfAn0qiGYbMlodEl8yPQy39st-rsZ6DFl--sgKgfTfdrhYId7HA1NbOYJrlgy3t454_GAVaLWiP6Z1PHJKktvB3EJ48_cFPXgaFcidUoA_fRqhHUZ9il388YZtKTE290e8yKDg9KuSYPVm8p6sHUep7iPl"
      }
    ]
  }
}